Workbook

Sheet products_2026
A1: product_id | B1: product_name | C1: product_category | D1: product_price_aud | E1: seller_id
A2: PROD00001 | B2: Hair Strengthening Mask shea butter 4 pack | C2: Beauty | D2: 33.08 | E2: SELL0001
A3: PROD00002 | B3: Hair Strengthening Mask shea butter 2 pack | C3: Beauty | D3: 31.97 | E3: SELL0001
A4: PROD00003 | B4: Rain Jacket Light Green | C4: Clothes | D4: 47.09 | E4: SELL0002
A5: PROD00004 | B5: Wireless Keyboard | C5: Electronics | D5: 85.97 | E5: SELL0003
A6: PROD00005 | B6: Wall Clock - Minimalist (Blue) | C6: Home | D6: 96.77 | E6: SELL0004
A7: PROD00006 | B7: Highlighter Set Bright 4 pen | C7: Stationery | D7: 4.47 | E7: SELL0005
A8: PROD00007 | B8: Slime Lab Blue 8pc | C8: Toys | D8: 38.25 | E8: SELL0006
A9: PROD00008 | B9: Slime Lab Green 8pc | C9: Toys | D9: 38.25 | E9: SELL0006
A10: PROD00009 | B10: Heat Therapy Pad | C10: Health | D10: 79.16 | E10: SELL0007
A11: PROD00010 | B11: Summer Dress - Floral | C11: Clothes | D11: 30.71 | E11: SELL0008
A12: PROD00011 | B12: Summer Dress - Floral Blue | C12: Clothes | D12: 30.12 | E12: SELL0008
A13: PROD00012 | B13: Whiteboard Markers - 6 pack | C13: Stationery | D13: 7.06 | E13: SELL0010
... A15: PROD00014 | B15: Waterproof Picnic Mat 100x100 | C15: Outdoor | D15: 46.45 | E15: SELL0012
A16: PROD00015 | B16: Garden Lights 4 pack Solar Power | C16: Outdoor | D16: 48.06 | E16: SELL0014 | H16: =SUM(Table3[product_price_aud]) -> 19738.69
A17: PROD00016 | B17: Stainless Steel Grill Basket XL | C17: Outdoor | D17: 73.55 | E17: SELL0015
A18: PROD00017 | B18: BBQ Skewers - 12 pack (Bamboo) | C18: Outdoor | D18: 13.71 | E18: SELL0016
A19: PROD00018 | B19: Waterproof Picnic Mat 100x100 | C19: Outdoor | D19: 40.12 | E19: SELL0016
A20: PROD00019 | B20: Hydrating Face Mist | C20: Beauty | D20: 10.94 | E20: SELL0017
A21: PROD00020 | B21: BBQ Skewers - 12 pack (Stainless Steel) | C21: Outdoor | D21: 15.05 | E21: SELL0009
A22: PROD00021 | B22: Garden Lights 10 pack Solar Power | C22: Outdoor | D22: 113.99 | E22: SELL0017
A23: PROD00022 | B23: BBQ Skewers - 24 pack (Stainless Steel) | C23: Outdoor | D23: 27.05 | E23: SELL0018
A24: PROD00023 | B24: Stainless Steel Grill Basket XL | C24: Outdoor | D24: 98.38 | E24: SELL0018
A25: PROD00024 | B25: BBQ Skewers - 24 pack (Bamboo) | C25: Outdoor | D25: 23.99 | E25: SELL0018
A26: PROD00025 | B26: Vit C Serum Revitalising 50ml | C26: Beauty | D26: 11.28 | E26: SELL0018
A27: PROD00026 | B27: Digital Thermometer (Yellow) | C27: Health | D27: 43.18 | E27: SELL0018
A28: PROD00027 | B28: Pendant Necklace - Rose Gold | C28: Jewellery | D28: 28.22 | E28: SELL0019
... A251: PROD00250 | B251: Highlighter 4pc Yellow | C251: Stationery | D251: 6.18 | E251: SELL0080
A252: PROD00251 | B252: Waterproof Picnic Mat Pattern | C252: Outdoor | D252: 70.39 | E252: SELL0081 | G252: =SUM(D15:D462) -> 19141.16
A253: PROD00252 | B253: Men’s Chino Shorts M | C253: Clothes | D253: 56.67 | E253: SELL0081
A254: PROD00253 | B254: Milk Chocolate Selection Box | C254: Gift_Sets | D254: 19.09 | E254: SELL0081
A255: PROD00254 | B255: Charm Bracelet 3 charms silver | C255: Jewellery | D255: 56.43 | E255: SELL0081
A256: PROD00255 | B256: Wood Chips - Hickory | C256: Outdoor | D256: 31.66 | E256: SELL0081
A257: PROD00256 | B257: Disposible Mini Grill | C257: Outdoor | D257: 48.14 | E257: SELL0081
A258: PROD00257 | B258: Face Mist Vitamin E | C258: Beauty | D258: 17.28 | E258: SELL0082
A259: PROD00258 | B259: Luxury Makeup Sponge Blend | C259: Beauty | D259: 31.59 | E259: SELL0082
A260: PROD00259 | B260: Hair Strengthening Mask shea butter | C260: Beauty | D260: 22.28 | E260: SELL0082
A261: PROD00260 | B261: Aloe Vera Gel 150ml | C261: Beauty | D261: 11.75 | E261: SELL0083
A262: PROD00261 | B262: Aloe Vera Gel 200ml | C262: Beauty | D262: 6.91 | E262: SELL0083
A263: PROD00262 | B263: Vitamin C Serum 50ml | C263: Beauty | D263: 15.09 | E263: SELL0001
A264: PROD00263 | B264: Memory Foam Pillow Medium Firm x 2 | C264: Home | D264: 119.3 | E264: SELL0078
... A463: PROD00462 | B463: Wooden Train Set | C463: Toys | D463: 37.23 | E463: SELL0095

Sheet Rough data
A1: product_category | B1: product_id | C1: product_price | D1: product_name | E1: seller_id | F1: seller_user | G1: product_quantity | H1: product_revenue
A2: =VLOOKUP(B2,Table3[[#Headers],[#Data]],3,FALSE) -> Beauty | B2: PROD00001 | C2: =VLOOKUP(B2,Table3[[#Headers],[#Data]],4, FALSE) -> 33.08 | D2: =VLOOKUP('Rough data'!B2,Table3[[#Headers],[#Data]],2,FALSE) -> Hair Strengthening Mask shea butter 4 pack | E2: =VLOOKUP(B2,Table3[[#Headers],[#Data]],5,FALSE) -> SELL0001 | F2: =VLOOKUP(E2,Table2[[#Headers],[#Data],[seller_id]:[seller_user]],2,FALSE) -> beauty4everyone | G2: 1 | H2: =G2*C2 -> 33.08
A3: =VLOOKUP(B3,Table3[[#Headers],[#Data]],3,FALSE) -> Stationery | B3: PROD00006 | C3: =VLOOKUP(B3,Table3[[#Headers],[#Data]],4, FALSE) -> 4.47 | D3: =VLOOKUP('Rough data'!B3,Table3[[#Headers],[#Data]],2,FALSE) -> Highlighter Set Bright 4 pen | E3: =VLOOKUP(B3,Table3[[#Headers],[#Data]],5,FALSE) -> SELL0005 | F3: =VLOOKUP(E3,Table2[[#Headers],[#Data],[seller_id]:[seller_user]],2,FALSE) -> pensandthings | G3: 2 | H3: =G3*C3 -> 8.94
A4: =VLOOKUP(B4,Table3[[#Headers],[#Data]],3,FALSE) -> Stationery | B4: PROD00006 | C4: =VLOOKUP(B4,Table3[[#Headers],[#Data]],4, FALSE) -> 4.47 | D4: =VLOOKUP('Rough data'!B4,Table3[[#Headers],[#Data]],2,FALSE) -> Highlighter Set Bright 4 pen | E4: =VLOOKUP(B4,Table3[[#Headers],[#Data]],5,FALSE) -> SELL0005 | F4: =VLOOKUP(E4,Table2[[#Headers],[#Data],[seller_id]:[seller_user]],2,FALSE) -> pensandthings | G4: 1 | H4: =G4*C4 -> 4.47
A5: =VLOOKUP(B5,Table3[[#Headers],[#Data]],3,FALSE) -> Toys | B5: PROD00007 | C5: =VLOOKUP(B5,Table3[[#Headers],[#Data]],4, FALSE) -> 38.25 | D5: =VLOOKUP('Rough data'!B5,Table3[[#Headers],[#Data]],2,FALSE) -> Slime Lab Blue 8pc | E5: =VLOOKUP(B5,Table3[[#Headers],[#Data]],5,FALSE) -> SELL0006 | F5: =VLOOKUP(E5,Table2[[#Headers],[#Data],[seller_id]:[seller_user]],2,FALSE) -> toysyay | G5: 1 | H5: =G5*C5 -> 38.25
A6: =VLOOKUP(B6,Table3[[#Headers],[#Data]],3,FALSE) -> Toys | B6: PROD00008 | C6: =VLOOKUP(B6,Table3[[#Headers],[#Data]],4, FALSE) -> 38.25 | D6: =VLOOKUP('Rough data'!B6,Table3[[#Headers],[#Data]],2,FALSE) -> Slime Lab Green 8pc | E6: =VLOOKUP(B6,Table3[[#Headers],[#Data]],5,FALSE) -> SELL0006 | F6: =VLOOKUP(E6,Table2[[#Headers],[#Data],[seller_id]:[seller_user]],2,FALSE) -> toysyay | G6: 1 | H6: =G6*C6 -> 38.25
A7: =VLOOKUP(B7,Table3[[#Headers],[#Data]],3,FALSE) -> Toys | B7: PROD00008 | C7: =VLOOKUP(B7,Table3[[#Headers],[#Data]],4, FALSE) -> 38.25 | D7: =VLOOKUP('Rough data'!B7,Table3[[#Headers],[#Data]],2,FALSE) -> Slime Lab Green 8pc | E7: =VLOOKUP(B7,Table3[[#Headers],[#Data]],5,FALSE) -> SELL0006 | F7: =VLOOKUP(E7,Table2[[#Headers],[#Data],[seller_id]:[seller_user]],2,FALSE) -> toysyay | G7: 1 | H7: =G7*C7 -> 38.25
A8: =VLOOKUP(B8,Table3[[#Headers],[#Data]],3,FALSE) -> Clothes | B8: PROD00010 | C8: =VLOOKUP(B8,Table3[[#Headers],[#Data]],4, FALSE) -> 30.71 | D8: =VLOOKUP('Rough data'!B8,Table3[[#Headers],[#Data]],2,FALSE) -> Summer Dress - Floral | E8: =VLOOKUP(B8,Table3[[#Headers],[#Data]],5,FALSE) -> SELL0008 | F8: =VLOOKUP(E8,Table2[[#Headers],[#Data],[seller_id]:[seller_user]],2,FALSE) -> peterpiper | G8: 1 | H8: =G8*C8 -> 30.71
A9: =VLOOKUP(B9,Table3[[#Headers],[#Data]],3,FALSE) -> Clothes | B9: PROD00010 | C9: =VLOOKUP(B9,Table3[[#Headers],[#Data]],4, FALSE) -> 30.71 | D9: =VLOOKUP('Rough data'!B9,Table3[[#Headers],[#Data]],2,FALSE) -> Summer Dress - Floral | E9: =VLOOKUP(B9,Table3[[#Headers],[#Data]],5,FALSE) -> SELL0008 | F9: =VLOOKUP(E9,Table2[[#Headers],[#Data],[seller_id]:[seller_user]],2,FALSE) -> peterpiper | G9: 1 | H9: =G9*C9 -> 30.71
A10: =VLOOKUP(B10,Table3[[#Headers],[#Data]],3,FALSE) -> Stationery | B10: PROD00012 | C10: =VLOOKUP(B10,Table3[[#Headers],[#Data]],4, FALSE) -> 7.06 | D10: =VLOOKUP('Rough data'!B10,Table3[[#Headers],[#Data]],2,FALSE) -> Whiteboard Markers - 6 pack | E10: =VLOOKUP(B10,Table3[[#Headers],[#Data]],5,FALSE) -> SELL0010 | F10: =VLOOKUP(E10,Table2[[#Headers],[#Data],[seller_id]:[seller_user]],2,FALSE) -> hobbylobby | G10: 2 | H10: =G10*C10 -> 14.12
A11: =VLOOKUP(B11,Table3[[#Headers],[#Data]],3,FALSE) -> Stationery | B11: PROD00012 | C11: =VLOOKUP(B11,Table3[[#Headers],[#Data]],4, FALSE) -> 7.06 | D11: =VLOOKUP('Rough data'!B11,Table3[[#Headers],[#Data]],2,FALSE) -> Whiteboard Markers - 6 pack | E11: =VLOOKUP(B11,Table3[[#Headers],[#Data]],5,FALSE) -> SELL0010 | F11: =VLOOKUP(E11,Table2[[#Headers],[#Data],[seller_id]:[seller_user]],2,FALSE) -> hobbylobby | G11: 2 | H11: =G11*C11 -> 14.12
A12: =VLOOKUP(B12,Table3[[#Headers],[#Data]],3,FALSE) -> Health | B12: PROD00013 | C12: =VLOOKUP(B12,Table3[[#Headers],[#Data]],4, FALSE) -> 37.4 | D12: =VLOOKUP('Rough data'!B12,Table3[[#Headers],[#Data]],2,FALSE) -> Heat Therapy Pad | E12: =VLOOKUP(B12,Table3[[#Headers],[#Data]],5,FALSE) -> SELL0011 | F12: =VLOOKUP(E12,Table2[[#Headers],[#Data],[seller_id]:[seller_user]],2,FALSE) -> dr-green | G12: 2 | H12: =G12*C12 -> 74.8
A13: =VLOOKUP(B13,Table3[[#Headers],[#Data]],3,FALSE) -> Outdoor | B13: PROD00014 | C13: =VLOOKUP(B13,Table3[[#Headers],[#Data]],4, FALSE) -> 46.45 | D13: =VLOOKUP('Rough data'!B13,Table3[[#Headers],[#Data]],2,FALSE) -> Waterproof Picnic Mat 100x100 | E13: =VLOOKUP(B13,Table3[[#Headers],[#Data]],5,FALSE) -> SELL0012 | F13: =VLOOKUP(E13,Table2[[#Headers],[#Data],[seller_id]:[seller_user]],2,FALSE) -> jane-outside | G13: 1 | H13: =G13*C13 -> 46.45
... A796: =VLOOKUP(B796,Table3[[#Headers],[#Data]],3,FALSE) -> Outdoor | B796: PROD00461 | C796: =VLOOKUP(B796,Table3[[#Headers],[#Data]],4, FALSE) -> 21 | D796: =VLOOKUP('Rough data'!B796,Table3[[#Headers],[#Data]],2,FALSE) -> Wooden Train Set | E796: =VLOOKUP(B796,Table3[[#Headers],[#Data]],5,FALSE) -> SELL0047 | F796: =VLOOKUP(E796,Table2[[#Headers],[#Data],[seller_id]:[seller_user]],2,FALSE) -> toymajoy | G796: 1 | H796: =G796*C796 -> 21

Sheet PT FOR Q3
D1: product_name | E1: Sum of product_revenue | G1: seller_user | H1: Sum of product_revenue | J1: seller_user | K1: Sum of product_quantity
D2: Adjustable Dumbbell 10kg | E2: 116.75 | G2: 1bt8plshsf | H2: 339.42 | J2: 1bt8plshsf | K2: 5
A3: product_category | B3: Sum of product_revenue | D3: Adjustable Dumbbell 12kg | E3: 182.58 | G3: 3n2ybcn0e4 | H3: 16.11 | J3: 3n2ybcn0e4 | K3: 1
A4: Beauty | B4: 1239.08 | D4: Adjustable Dumbbell 15kg | E4: 257.82 | G4: 7e16xoz37j | H4: 146.81 | J4: 7e16xoz37j | K4: 4
A5: Clothes | B5: 3487.24 | D5: Adjustable Dumbbell 20kg | E5: 77.97 | G5: 7ti9lfa6h5 | H5: 2038.12 | J5: 7ti9lfa6h5 | K5: 49
A6: Electronics | B6: 4385.23 | D6: Adjustable Dumbbell 25kg | E6: 60.93 | G6: abracadabra_002 | H6: 514.92 | J6: abracadabra_002 | K6: 26
A7: Gift_Sets | B7: 1807.1 | D7: Adjustable Dumbbell 8kg | E7: 75.4 | G7: au6ynzdcy5 | H7: 713.98 | J7: au6ynzdcy5 | K7: 14
A8: Health | B8: 2178.86 | D8: Aloe Vera Gel 150ml 2 pack | E8: 53 | G8: b8iv8o4c65 | H8: 133.02 | J8: b8iv8o4c65 | K8: 3
A9: Home | B9: 6457.93 | D9: Aloe Vera Gel 200ml | E9: 13.82 | G9: barbievend | H9: 82.71 | J9: barbievend | K9: 2
A10: Jewellery | B10: 1829.68 | D10: Aloe Vera Gel 200ml 2 pack | E10: 38.74 | G10: beautifullhome | H10: 1634.81 | J10: beautifullhome | K10: 27
A11: Outdoor | B11: 16526.25 | D11: Aloe Vera Gel 500ml | E11: 53.49 | G11: beautifullife472 | H11: 275.93 | J11: beautifullife472 | K11: 10
A12: Stationery | B12: 351.23 | D12: Anklet - Gold | E12: 13.95 | G12: beauty490 | H12: 653.91 | J12: beauty490 | K12: 14
A13: Toys | B13: 1434.61 | D13: Anklet - Silver Tone | E13: 75.52 | G13: beauty4everyone | H13: 111.68 | J13: beauty4everyone | K13: 4
A14: Grand Total | B14: 39697.21 | D14: antique bronze necklace owl vintage | E14: 49.4 | G14: blessedforall | H14: 135.96 | J14: blessedforall | K14: 7
D15: Baby Shower Gift Bundle (Blue) | E15: 32.89 | G15: bootsandcamping | H15: 135.45 | J15: bootsandcamping | K15: 9
D16: Baby Shower Gift Bundle (Yellow) | E16: 32.99 | G16: brizzy_bonanza_48 | H16: 539.25 | J16: brizzy_bonanza_48 | K16: 13
D17: Ballpoint pen 6 pack | E17: 8.72 | G17: buildmydream | H17: 487.35 | J17: buildmydream | K17: 8
D18: Bamboo Picnic Rug Recycled Material | E18: 201.4 | G18: buydongxi25 | H18: 119.5 | J18: buydongxi25 | K18: 5
D19: Bath Bomb Strawberry Vanilla Gift Set | E19: 189.2 | G19: buyeverything-1 | H19: 374.01 | J19: buyeverything-1 | K19: 6
D20: Bath Bomb Variety Pack (Rose lavender) | E20: 13.54 | G20: buyingtime | H20: 70.17 | J20: buyingtime | K20: 6
D21: Bath Bomb Variety Pack (Ylang ylang jasmine) | E21: 39.85 | G21: cheapandgood27 | H21: 334.19 | J21: cheapandgood27 | K21: 13
D22: BBQ - Charcoal | E22: 450.6 | G22: cleaning_out_my_shed | H22: 720.73 | J22: cleaning_out_my_shed | K22: 18
D23: BBQ Apron - Blue | E23: 560.49 | G23: clothes832 | H23: 108.34 | J23: clothes832 | K23: 2
D24: BBQ Apron - Red | E24: 291.51 | G24: clothesforlife | H24: 1075.58 | J24: clothesforlife | K24: 29
D25: BBQ Cleaning Brush | E25: 464.25 | G25: compradadonut | H25: 437.84 | J25: compradadonut | K25: 8
D26: BBQ Cleaning Brush XXL | E26: 363.95 | G26: cpghfp370y | H26: 24.72 | J26: cpghfp370y | K26: 4
... D88: Face mask peel-off orange 3 pack | E88: 50 | G88: zmkizlf6t6 | H88: 808.1 | J88: zmkizlf6t6 | K88: 23
D89: Face Mist Vitamin E | E89: 69.12 | G89: (blank) | J89: (blank)
D90: Fairy Lights Outdoor Garden String 100 | E90: 460.68 | G90: Grand Total | H90: 39697.21 | J90: Grand Total | K90: 940
D91: Fairy Lights Outdoor Garden String 200 | E91: 111.78
D92: Floor Lamp Standing Tall LED | E92: 248.64
D93: Foam Maker | E93: 37.98
D94: Foam Roller - Firm Black | E94: 43.01
D95: Foam Roller - Firm Blue Large | E95: 98.42
D96: Fruity Mango Bath Gel Gift Set | E96: 72.78
D97: Gaming Mouse | E97: 53.16
D98: Garden Hose 20m (Green) | E98: 57.98
D99: Garden Hose 20m (Grey) | E99: 167.97
D100: Garden Hose 50m (Green) | E100: 262.53
D101: Garden Hose 50m (Grey) | E101: 96.77
D102: Garden Light Sun Powered No Recharge | E102: 439.29
... D317: Yoga Mat 10mm | E317: 116.46
D318: (blank)
D319: Grand Total | E319: 39697.21

Sheet sellers_2026
A1: seller_id | B1: seller_user | C1: seller_name | D1: seller_surname | E1: seller_email | F1: seller_area | G1: seller_state
A2: SELL0001 | B2: beauty4everyone | C2: Mariah | D2: Davila | E2: mdavila8@gmail.com | F2: Cloncurry | G2: VIC | I2: Row Labels | J2: Count of seller_id
A3: SELL0002 | B3: wan-yifu | C3: Li | D3: Mei | E3: lmei@hotmail.com | F3: Adelaide | G3: SA | I3: ACT | J3: 8
A4: SELL0003 | B4: electroshop | C4: Persephone | D4: Horne | E4: electroshop@aol.com | F4: Albany | G4: WA | I4: NSW | J4: 10
A5: SELL0004 | B5: nol6svwlnf | C5: Zee | D5: Dodson | E5: nol6svwlnf@optusnet.com.au | F5: Gawler | G5: SA | I5: NT | J5: 13
A6: SELL0005 | B6: pensandthings | C6: Etta | D6: Conway | E6: ett-conway72@gmail.com | F6: Launceston | G6: TAS | I6: QLD | J6: 15
A7: SELL0006 | B7: toysyay | C7: Oliver | D7: Flowers | E7: oflowers7@microsoft.com | F7: Bendigo | G7: VIC | I7: SA | J7: 7
A8: SELL0007 | B8: healthy_habits | C8: Ariya | D8: Harmon | E8: healthy_habits@gmail.com | F8: Townsville | G8: QLD | I8: TAS | J8: 13
A9: SELL0008 | B9: peterpiper | C9: Peter | D9: Stafford | E9: peter-stafford1982@gmail.com | F9: Winton | G9: QLD | I9: VIC | J9: 19
A10: SELL0009 | B10: bootsandcamping | C10: Bridget | D10: Fisher | E10: bridget_fisher@microsoft.com | F10: Toowoomba | G10: QLD | I10: WA | J10: 10
A11: SELL0010 | B11: hobbylobby | C11: Gordon | D11: O'Flannagan | E11: hobbylobby@microsoft.com | F11: Melbourne | G11: VIC | I11: (blank)
A12: SELL0011 | B12: dr-green | C12: Giuliana | D12: Green | E12: ggreen@optusnet.com.au | F12: Brisbane | G12: QLD | I12: Grand Total | J12: 95
A13: SELL0012 | B13: jane-outside | C13: Jane | D13: Little | E13: jane-little@gmail.com | F13: Kalgoorlie | G13: WA
A14: SELL0013 | B14: slln3xj7zl | C14: Alice | D14: Daniels | E14: alidaniels58@gmail.com | F14: Adelaide | G14: SA
A15: SELL0014 | B15: gardenandco | C15: Xander | D15: Lester | E15: xlester@hotmail.com | F15: Canberra | G15: ACT
A16: SELL0015 | B16: outhomelovely | C16: Averi | D16: Glenn | E16: aglenn@hotmail.com | F16: Newcastle | G16: NSW
A17: SELL0016 | B17: abracadabra_002 | C17: Zaid | D17: Blake | E17: zaid-blake@gmail.com | F17: Strahan | G17: TAS
A18: SELL0017 | B18: 7e16xoz37j | C18: Amanda | D18: Doyle | E18: adoyle8@live.au | F18: Rockhampton | G18: QLD
A19: SELL0018 | B19: darwin_beauty | C19: Karly | D19: Bowers | E19: k.bowers@gmail.com | F19: Darwin | G19: NT
A20: SELL0019 | B20: buyingtime | C20: Elisa | D20: Foster | E20: elisa_foster1993@gmail.com | F20: Mareeba | G20: QLD
A21: SELL0020 | B21: staion-bonanza | C21: Christian | D21: Mcdonald | E21: staion-bonanza@hotmail.com | F21: Darwin | G21: NT
A22: SELL0021 | B22: stuff-on-sale | C22: Daisy | D22: Cano | E22: dcano@hotmail.com | F22: Melbourne | G22: VIC
A23: SELL0022 | B23: g5x9v55sct | C23: Terry | D23: Gibbs | E23: tgibbs5@microsoft.com | F23: Bunbury | G23: WA
A24: SELL0023 | B24: cleaning_out_my_shed | C24: Colin | D24: Curry | E24: c.curry@gmail.com | F24: Bendigo | G24: VIC
... A96: SELL0095 | B96: toybuy | C96: Benji | D96: Lang | E96: blang@hotmail.com | F96: Port Lincoln | G96: TAS

Sheet customers
A1: customer_id | B1: customer_email | C1: customer_name | D1: customer_surname | E1: customer_area | F1: customer_state | G1: total_customer_spend | H1: number_of_orders | I1: Customer_type
A2: CUST00001 | B2: freya95@bigpond.com.au | C2: Freya | D2: Adams | E2: Darwin | F2: NT | G2: =SUMIF(orders!B:B,A2,orders!F:F) -> 0 | H2: =COUNTIF(orders!B:B,A2) -> 0 | I2: =IF(H2>1,"Repeat Customer","One-Time Customer") -> One-Time Customer
A3: CUST00002 | B3: charliesat@bigpond.com.au | C3: Charles | D3: Sato | E3: Central Coast | F3: NSW | G3: =SUMIF(orders!B:B,A3,orders!F:F) -> 0 | H3: =COUNTIF(orders!B:B,A3) -> 0 | I3: =IF(H3>1,"Repeat Customer","One-Time Customer") -> One-Time Customer
A4: CUST00003 | B4: jack26@gmail.com | C4: Jack | D4: Petrov | E4: Ballarat | F4: VIC | G4: =SUMIF(orders!B:B,A4,orders!F:F) -> 430.15 | H4: =COUNTIF(orders!B:B,A4) -> 3 | I4: =IF(H4>1,"Repeat Customer","One-Time Customer") -> Repeat Customer | M4: Row Labels | N4: Count of customer_id | O4: visual 1 customers by state
A5: CUST00004 | B5: footy.minh@live.au | C5: Minh | D5: Pham | E5: Broken Hill | F5: NSW | G5: =SUMIF(orders!B:B,A5,orders!F:F) -> 70.83 | H5: =COUNTIF(orders!B:B,A5) -> 2 | I5: =IF(H5>1,"Repeat Customer","One-Time Customer") -> Repeat Customer | M5: ACT | N5: 4
A6: CUST00005 | B6: bianchi.aurora@outlook.com | C6: Aurora | D6: Bianchi | E6: Kalgoorlie | F6: WA | G6: =SUMIF(orders!B:B,A6,orders!F:F) -> 49.22 | H6: =COUNTIF(orders!B:B,A6) -> 2 | I6: =IF(H6>1,"Repeat Customer","One-Time Customer") -> Repeat Customer | M6: NSW | N6: 141 | O6: NSW is CompradaRoo's largest customer market, accounting for approximately 32% of all customers (141 of 441).
A7: CUST00006 | B7: noah.jameson@outlook.com | C7: Noah | D7: Jameson | E7: Coffs Harbour | F7: NSW | G7: =SUMIF(orders!B:B,A7,orders!F:F) -> 418.57 | H7: =COUNTIF(orders!B:B,A7) -> 7 | I7: =IF(H7>1,"Repeat Customer","One-Time Customer") -> Repeat Customer | M7: NT | N7: 5
A8: CUST00007 | B8: lucas1997@bigpond.com.au | C8: Luca | D8: Gomez | E8: Townsville | F8: QLD | G8: =SUMIF(orders!B:B,A8,orders!F:F) -> 29.85 | H8: =COUNTIF(orders!B:B,A8) -> 1 | I8: =IF(H8>1,"Repeat Customer","One-Time Customer") -> One-Time Customer | M8: QLD | N8: 96
A9: CUST00008 | B9: tanaka.sienna@outlook.com | C9: Sienna | D9: Tanaka | E9: Sydney | F9: NSW | G9: =SUMIF(orders!B:B,A9,orders!F:F) -> 56.31 | H9: =COUNTIF(orders!B:B,A9) -> 2 | I9: =IF(H9>1,"Repeat Customer","One-Time Customer") -> Repeat Customer | M9: SA | N9: 26
A10: CUST00009 | B10: urbanedward@microsoft.com | C10: Edward | D10: Silver | E10: Dubbo | F10: NSW | G10: =SUMIF(orders!B:B,A10,orders!F:F) -> 0 | H10: =COUNTIF(orders!B:B,A10) -> 0 | I10: =IF(H10>1,"Repeat Customer","One-Time Customer") -> One-Time Customer | M10: TAS | N10: 14
A11: CUST00010 | B11: turner.hiro@gmail.com | C11: Hiro | D11: Turner | E11: Hervey Bay | F11: QLD | G11: =SUMIF(orders!B:B,A11,orders!F:F) -> 727.08 | H11: =COUNTIF(orders!B:B,A11) -> 6 | I11: =IF(H11>1,"Repeat Customer","One-Time Customer") -> Repeat Customer | M11: VIC | N11: 109
A12: CUST00011 | B12: lucas.deluca@outlook.com | C12: Lindsay | D12: DeLuca | E12: Sydney | F12: NSW | G12: =SUMIF(orders!B:B,A12,orders!F:F) -> 340.97 | H12: =COUNTIF(orders!B:B,A12) -> 4 | I12: =IF(H12>1,"Repeat Customer","One-Time Customer") -> Repeat Customer | M12: WA | N12: 46
A13: CUST00012 | B13: charliecharliecharlie@outlook.com | C13: Charlotte | D13: Walker | E13: Bendigo | F13: VIC | G13: =SUMIF(orders!B:B,A13,orders!F:F) -> 139.02 | H13: =COUNTIF(orders!B:B,A13) -> 2 | I13: =IF(H13>1,"Repeat Customer","One-Time Customer") -> Repeat Customer | M13: Grand Total | N13: 441
A14: CUST00013 | B14: coffee.tom@gmail.com | C14: Thomas | D14: Ngata | E14: Dubbo | F14: NSW | G14: =SUMIF(orders!B:B,A14,orders!F:F) -> 114.29 | H14: =COUNTIF(orders!B:B,A14) -> 2 | I14: =IF(H14>1,"Repeat Customer","One-Time Customer") -> Repeat Customer
A15: CUST00014 | B15: latelucas@optusnet.com.au | C15: Lucas | D15: Faatua | E15: Coffs Harbour | F15: NSW | G15: =SUMIF(orders!B:B,A15,orders!F:F) -> 145.38 | H15: =COUNTIF(orders!B:B,A15) -> 2 | I15: =IF(H15>1,"Repeat Customer","One-Time Customer") -> Repeat Customer
A16: CUST00015 | B16: tom_684@microsoft.com | C16: Thomas | D16: Green | E16: Brisbane | F16: QLD | G16: =SUMIF(orders!B:B,A16,orders!F:F) -> 312.39 | H16: =COUNTIF(orders!B:B,A16) -> 5 | I16: =IF(H16>1,"Repeat Customer","One-Time Customer") -> Repeat Customer
A17: CUST00016 | B17: aaarav@gmail.com | C17: Aarav | D17: Costa | E17: Cairns | F17: QLD | G17: =SUMIF(orders!B:B,A17,orders!F:F) -> 46.28 | H17: =COUNTIF(orders!B:B,A17) -> 1 | I17: =IF(H17>1,"Repeat Customer","One-Time Customer") -> One-Time Customer
A18: CUST00017 | B18: redpoppy2574@aol.com | C18: Poppy | D18: Liu | E18: Darwin | F18: NT | G18: =SUMIF(orders!B:B,A18,orders!F:F) -> 161.5 | H18: =COUNTIF(orders!B:B,A18) -> 4 | I18: =IF(H18>1,"Repeat Customer","One-Time Customer") -> Repeat Customer
A19: CUST00018 | B19: sophie83@gmail.com | C19: Sophy | D19: Ali | E19: Port Lincoln | F19: SA | G19: =SUMIF(orders!B:B,A19,orders!F:F) -> 112.68 | H19: =COUNTIF(orders!B:B,A19) -> 3 | I19: =IF(H19>1,"Repeat Customer","One-Time Customer") -> Repeat Customer
A20: CUST00019 | B20: thuy.travel@live.au | C20: Thuy | D20: Anderson | E20: Adelaide | F20: SA | G20: =SUMIF(orders!B:B,A20,orders!F:F) -> 0 | H20: =COUNTIF(orders!B:B,A20) -> 0 | I20: =IF(H20>1,"Repeat Customer","One-Time Customer") -> One-Time Customer
A21: CUST00020 | B21: wturner@microsoft.com | C21: Willow | D21: Turner | E21: Geelong | F21: VIC | G21: =SUMIF(orders!B:B,A21,orders!F:F) -> 0 | H21: =COUNTIF(orders!B:B,A21) -> 0 | I21: =IF(H21>1,"Repeat Customer","One-Time Customer") -> One-Time Customer
A22: CUST00021 | B22: luna.footy@hotmail.com | C22: Luna | D22: Lee | E22: Coffs Harbour | F22: NSW | G22: =SUMIF(orders!B:B,A22,orders!F:F) -> 0 | H22: =COUNTIF(orders!B:B,A22) -> 0 | I22: =IF(H22>1,"Repeat Customer","One-Time Customer") -> One-Time Customer | M22: customer_state | N22: Sum of total_customer_spend | O22: visual 2 revenue by state
A23: CUST00022 | B23: oliver.liu@gmail.com | C23: Oliver | D23: Liu | E23: Brisbane | F23: QLD | G23: =SUMIF(orders!B:B,A23,orders!F:F) -> 304.61 | H23: =COUNTIF(orders!B:B,A23) -> 2 | I23: =IF(H23>1,"Repeat Customer","One-Time Customer") -> Repeat Customer | M23: ACT | N23: 356.67
A24: CUST00023 | B24: matildaanderson@optusnet.com.au | C24: Matilda | D24: Anderson | E24: Perth | F24: WA | G24: =SUMIF(orders!B:B,A24,orders!F:F) -> 45.71 | H24: =COUNTIF(orders!B:B,A24) -> 1 | I24: =IF(H24>1,"Repeat Customer","One-Time Customer") -> One-Time Customer | M24: NSW | N24: 12338.55 | O24: NSW generates the highest customer revenue, contributing around one-third of total platform revenue.
A25: CUST00024 | B25: anguswild@hotmail.com | C25: Andie | D25: Kitt | E25: Melbourne | F25: VIC | G25: =SUMIF(orders!B:B,A25,orders!F:F) -> 26.37 | H25: =COUNTIF(orders!B:B,A25) -> 1 | I25: =IF(H25>1,"Repeat Customer","One-Time Customer") -> One-Time Customer | M25: NT | N25: 272.25
A26: CUST00025 | B26: brown.ava@aol.com | C26: Ava | D26: Brown | E26: Sydney | F26: NSW | G26: =SUMIF(orders!B:B,A26,orders!F:F) -> 129.4 | H26: =COUNTIF(orders!B:B,A26) -> 4 | I26: =IF(H26>1,"Repeat Customer","One-Time Customer") -> Repeat Customer | M26: QLD | N26: 8255.85
A27: CUST00026 | B27: art.aurora@gmail.com | C27: Anya | D27: Kaur | E27: Newcastle | F27: NSW | G27: =SUMIF(orders!B:B,A27,orders!F:F) -> 63.26 | H27: =COUNTIF(orders!B:B,A27) -> 2 | I27: =IF(H27>1,"Repeat Customer","One-Time Customer") -> Repeat Customer | M27: SA | N27: 1987.83
A28: CUST00027 | B28: mason.murphy@hotmail.com | C28: Mason | D28: Murphy | E28: Byron Bay | F28: NSW | G28: =SUMIF(orders!B:B,A28,orders!F:F) -> 194.69 | H28: =COUNTIF(orders!B:B,A28) -> 2 | I28: =IF(H28>1,"Repeat Customer","One-Time Customer") -> Repeat Customer | M28: TAS | N28: 1161.99
A29: CUST00028 | B29: zoerossi@yahoo.com | C29: Zoe | D29: Rossi | E29: Sydney | F29: NSW | G29: =SUMIF(orders!B:B,A29,orders!F:F) -> 590.89 | H29: =COUNTIF(orders!B:B,A29) -> 7 | I29: =IF(H29>1,"Repeat Customer","One-Time Customer") -> Repeat Customer | M29: VIC | N29: 9985.15
A30: CUST00029 | B30: pham.amelia@hotmail.com | C30: Amelia | D30: Pham | E30: Bunbury | F30: WA | G30: =SUMIF(orders!B:B,A30,orders!F:F) -> 217.01 | H30: =COUNTIF(orders!B:B,A30) -> 3 | I30: =IF(H30>1,"Repeat Customer","One-Time Customer") -> Repeat Customer | M30: WA | N30: 3465.25
A31: CUST00030 | B31: photo.amelia@gmail.com | C31: Amelia | D31: Wilson | E31: Shepparton | F31: VIC | G31: =SUMIF(orders!B:B,A31,orders!F:F) -> 50.71 | H31: =COUNTIF(orders!B:B,A31) -> 1 | I31: =IF(H31>1,"Repeat Customer","One-Time Customer") -> One-Time Customer | M31: Grand Total | N31: 37823.54
A32: CUST00031 | B32: leebrrown@optusnet.com.au | C32: Lee | D32: Brown | E32: Sydney | F32: NSW | G32: =SUMIF(orders!B:B,A32,orders!F:F) -> 270.6 | H32: =COUNTIF(orders!B:B,A32) -> 4 | I32: =IF(H32>1,"Repeat Customer","One-Time Customer") -> Repeat Customer
A33: CUST00032 | B33: ekhan@yahoo.com | C33: Edward | D33: Khan | E33: Melbourne | F33: VIC | G33: =SUMIF(orders!B:B,A33,orders!F:F) -> 219.63 | H33: =COUNTIF(orders!B:B,A33) -> 2 | I33: =IF(H33>1,"Repeat Customer","One-Time Customer") -> Repeat Customer
A34: CUST00033 | B34: luiswild@gmail.com | C34: Luis | D34: Clerk | E34: Wagga Wagga | F34: NSW | G34: =SUMIF(orders!B:B,A34,orders!F:F) -> 190.95 | H34: =COUNTIF(orders!B:B,A34) -> 3 | I34: =IF(H34>1,"Repeat Customer","One-Time Customer") -> Repeat Customer
A35: CUST00034 | B35: sadie_153@microsoft.com | C35: Sadie | D35: Chen | E35: Rockhampton | F35: QLD | G35: =SUMIF(orders!B:B,A35,orders!F:F) -> 196.22 | H35: =COUNTIF(orders!B:B,A35) -> 2 | I35: =IF(H35>1,"Repeat Customer","One-Time Customer") -> Repeat Customer
A36: CUST00035 | B36: parks.sandy@gmail.com | C36: Sandy | D36: Parks | E36: Brisbane | F36: QLD | G36: =SUMIF(orders!B:B,A36,orders!F:F) -> 58.42 | H36: =COUNTIF(orders!B:B,A36) -> 1 | I36: =IF(H36>1,"Repeat Customer","One-Time Customer") -> One-Time Customer
A37: CUST00036 | B37: carls@outlook.com | C37: Carl | D37: Stewart | E37: Ballarat | F37: VIC | G37: =SUMIF(orders!B:B,A37,orders!F:F) -> 285.64 | H37: =COUNTIF(orders!B:B,A37) -> 3 | I37: =IF(H37>1,"Repeat Customer","One-Time Customer") -> Repeat Customer
A38: CUST00037 | B38: sienna_825@live.au | C38: Emma | D38: Papadopoulos | E38: Warrnambool | F38: VIC | G38: =SUMIF(orders!B:B,A38,orders!F:F) -> 343.41 | H38: =COUNTIF(orders!B:B,A38) -> 2 | I38: =IF(H38>1,"Repeat Customer","One-Time Customer") -> Repeat Customer
A39: CUST00038 | B39: grace_748@hotmail.com | C39: Grace | D39: Liu | E39: Brisbane | F39: QLD | G39: =SUMIF(orders!B:B,A39,orders!F:F) -> 0 | H39: =COUNTIF(orders!B:B,A39) -> 0 | I39: =IF(H39>1,"Repeat Customer","One-Time Customer") -> One-Time Customer
A40: CUST00039 | B40: ethan.turner@live.au | C40: Ethan | D40: Turner | E40: Rockhampton | F40: QLD | G40: =SUMIF(orders!B:B,A40,orders!F:F) -> 0 | H40: =COUNTIF(orders!B:B,A40) -> 0 | I40: =IF(H40>1,"Repeat Customer","One-Time Customer") -> One-Time Customer | M40: Row Labels | N40: Sum of total_customer_spend | O40: visual 3 repeat vsone time customers
A41: CUST00040 | B41: smurphy@aol.com | C41: Scarlett | D41: Murphy | E41: Sale | F41: VIC | G41: =SUMIF(orders!B:B,A41,orders!F:F) -> 0 | H41: =COUNTIF(orders!B:B,A41) -> 0 | I41: =IF(H41>1,"Repeat Customer","One-Time Customer") -> One-Time Customer | M41: One-Time Customer | N41: 5624.68 | O41: Repeat customers = 32% of customers
A42: CUST00041 | B42: cooper.rossi@gmail.com | C42: Cooper | D42: Rossi | E42: Sale | F42: VIC | G42: =SUMIF(orders!B:B,A42,orders!F:F) -> 197.69 | H42: =COUNTIF(orders!B:B,A42) -> 3 | I42: =IF(H42>1,"Repeat Customer","One-Time Customer") -> Repeat Customer | M42: Repeat Customer | N42: 32198.86 | O42: Repeat customers generate 85% of revenue
A43: CUST00042 | B43: tui.liam@bigpond.com.au | C43: Liam | D43: Toot | E43: Shepparton | F43: VIC | G43: =SUMIF(orders!B:B,A43,orders!F:F) -> 421.15 | H43: =COUNTIF(orders!B:B,A43) -> 3 | I43: =IF(H43>1,"Repeat Customer","One-Time Customer") -> Repeat Customer | M43: (blank)
A44: CUST00043 | B44: rileyking@yahoo.com | C44: Riley | D44: King | E44: Central Coast | F44: NSW | G44: =SUMIF(orders!B:B,A44,orders!F:F) -> 0 | H44: =COUNTIF(orders!B:B,A44) -> 0 | I44: =IF(H44>1,"Repeat Customer","One-Time Customer") -> One-Time Customer | M44: Grand Total | N44: 37823.54
A45: CUST00044 | B45: stella.golf@yahoo.com | C45: Stella | D45: Chen | E45: Coffs Harbour | F45: NSW | G45: =SUMIF(orders!B:B,A45,orders!F:F) -> 86.27 | H45: =COUNTIF(orders!B:B,A45) -> 1 | I45: =IF(H45>1,"Repeat Customer","One-Time Customer") -> One-Time Customer
A46: CUST00045 | B46: music.tom@live.au | C46: Thomas | D46: Green | E46: Byron Bay | F46: NSW | G46: =SUMIF(orders!B:B,A46,orders!F:F) -> 61.94 | H46: =COUNTIF(orders!B:B,A46) -> 3 | I46: =IF(H46>1,"Repeat Customer","One-Time Customer") -> Repeat Customer | M46: Row Labels | N46: Count of customer_id
A47: CUST00046 | B47: fatimasato@aol.com | C47: Fatima | D47: Sade | E47: Brisbane | F47: QLD | G47: =SUMIF(orders!B:B,A47,orders!F:F) -> 20.42 | H47: =COUNTIF(orders!B:B,A47) -> 1 | I47: =IF(H47>1,"Repeat Customer","One-Time Customer") -> One-Time Customer | M47: One-Time Customer | N47: 300
A48: CUST00047 | B48: tsato@yahoo.com | C48: Thomas | D48: Sato | E48: Adelaide | F48: SA | G48: =SUMIF(orders!B:B,A48,orders!F:F) -> 0 | H48: =COUNTIF(orders!B:B,A48) -> 0 | I48: =IF(H48>1,"Repeat Customer","One-Time Customer") -> One-Time Customer | M48: Repeat Customer | N48: 141
A49: CUST00048 | B49: bike.leo@outlook.com | C49: Leo | D49: Ali | E49: Sydney | F49: NSW | G49: =SUMIF(orders!B:B,A49,orders!F:F) -> 233.44 | H49: =COUNTIF(orders!B:B,A49) -> 3 | I49: =IF(H49>1,"Repeat Customer","One-Time Customer") -> Repeat Customer | M49: (blank)
A50: CUST00049 | B50: oscar.footy@gmail.com | C50: Oscar | D50: Adams | E50: Devonport | F50: TAS | G50: =SUMIF(orders!B:B,A50,orders!F:F) -> 87.32 | H50: =COUNTIF(orders!B:B,A50) -> 2 | I50: =IF(H50>1,"Repeat Customer","One-Time Customer") -> Repeat Customer | M50: Grand Total | N50: 441
A51: CUST00050 | B51: aarav2006@live.au | C51: Ali | D51: Zhang | E51: Sale | F51: VIC | G51: =SUMIF(orders!B:B,A51,orders!F:F) -> 188.99 | H51: =COUNTIF(orders!B:B,A51) -> 2 | I51: =IF(H51>1,"Repeat Customer","One-Time Customer") -> Repeat Customer
A52: CUST00051 | B52: blueleo@bigpond.com.au | C52: Leo | D52: Tomson | E52: Central Coast | F52: NSW | G52: =SUMIF(orders!B:B,A52,orders!F:F) -> 0 | H52: =COUNTIF(orders!B:B,A52) -> 0 | I52: =IF(H52>1,"Repeat Customer","One-Time Customer") -> One-Time Customer
A53: CUST00052 | B53: manucosta@outlook.com | C53: Manni | D53: Costa | E53: Cradle Mountain | F53: TAS | G53: =SUMIF(orders!B:B,A53,orders!F:F) -> 149.52 | H53: =COUNTIF(orders!B:B,A53) -> 3 | I53: =IF(H53>1,"Repeat Customer","One-Time Customer") -> Repeat Customer | M53: Row Labels | N53: Average of total_customer_spend
A54: CUST00053 | B54: darcy1995@yahoo.com | C54: Darcy | D54: Liu | E54: Brisbane | F54: QLD | G54: =SUMIF(orders!B:B,A54,orders!F:F) -> 42.49 | H54: =COUNTIF(orders!B:B,A54) -> 2 | I54: =IF(H54>1,"Repeat Customer","One-Time Customer") -> Repeat Customer | M54: ACT | N54: 89.1675
A55: CUST00054 | B55: finnivanov@hotmail.com | C55: Finn | D55: Ivanov | E55: Victor Harbor | F55: SA | G55: =SUMIF(orders!B:B,A55,orders!F:F) -> 34.62 | H55: =COUNTIF(orders!B:B,A55) -> 2 | I55: =IF(H55>1,"Repeat Customer","One-Time Customer") -> Repeat Customer | M55: NSW | N55: 87.507447
A56: CUST00055 | B56: martin.jack@hotmail.com | C56: Jack | D56: Martin | E56: Geraldton | F56: WA | G56: =SUMIF(orders!B:B,A56,orders!F:F) -> 14.5 | H56: =COUNTIF(orders!B:B,A56) -> 1 | I56: =IF(H56>1,"Repeat Customer","One-Time Customer") -> One-Time Customer | M56: NT | N56: 54.45
A57: CUST00056 | B57: george.walker@yahoo.com | C57: George | D57: Walker | E57: Dubbo | F57: NSW | G57: =SUMIF(orders!B:B,A57,orders!F:F) -> 122.16 | H57: =COUNTIF(orders!B:B,A57) -> 1 | I57: =IF(H57>1,"Repeat Customer","One-Time Customer") -> One-Time Customer | M57: QLD | N57: 85.998437
A58: CUST00057 | B58: oliver.martin@gmail.com | C58: Oliver | D58: Martin | E58: Brisbane | F58: QLD | G58: =SUMIF(orders!B:B,A58,orders!F:F) -> 0 | H58: =COUNTIF(orders!B:B,A58) -> 0 | I58: =IF(H58>1,"Repeat Customer","One-Time Customer") -> One-Time Customer | M58: SA | N58: 76.455
A59: CUST00058 | B59: earlylucas@outlook.com | C59: Lucas | D59: Kim | E59: Geelong | F59: VIC | G59: =SUMIF(orders!B:B,A59,orders!F:F) -> 86.6 | H59: =COUNTIF(orders!B:B,A59) -> 2 | I59: =IF(H59>1,"Repeat Customer","One-Time Customer") -> Repeat Customer | M59: TAS | N59: 82.999286
A60: CUST00059 | B60: alex.bake@microsoft.com | C60: Alexander | D60: Kelly | E60: Wollongong | F60: NSW | G60: =SUMIF(orders!B:B,A60,orders!F:F) -> 285.82 | H60: =COUNTIF(orders!B:B,A60) -> 2 | I60: =IF(H60>1,"Repeat Customer","One-Time Customer") -> Repeat Customer | M60: VIC | N60: 91.606881
A61: CUST00060 | B61: maria1990@bigpond.com.au | C61: Maria | D61: Smith | E61: Townsville | F61: QLD | G61: =SUMIF(orders!B:B,A61,orders!F:F) -> 437.69 | H61: =COUNTIF(orders!B:B,A61) -> 3 | I61: =IF(H61>1,"Repeat Customer","One-Time Customer") -> Repeat Customer | M61: WA | N61: 75.331522
A62: CUST00061 | B62: dan2003@bigpond.com.au | C62: Daniel | D62: Collins | E62: Melbourne | F62: VIC | G62: =SUMIF(orders!B:B,A62,orders!F:F) -> 59.27 | H62: =COUNTIF(orders!B:B,A62) -> 2 | I62: =IF(H62>1,"Repeat Customer","One-Time Customer") -> Repeat Customer | M62: (blank)
A63: CUST00062 | B63: bcarter@gmail.com | C63: Bonnie | D63: Jameson | E63: Sydney | F63: NSW | G63: =SUMIF(orders!B:B,A63,orders!F:F) -> 0 | H63: =COUNTIF(orders!B:B,A63) -> 0 | I63: =IF(H63>1,"Repeat Customer","One-Time Customer") -> One-Time Customer | M63: Grand Total | N63: 85.767664
A64: CUST00063 | B64: sunita.park@live.au | C64: Sunita | D64: Park | E64: Sydney | F64: NSW | G64: =SUMIF(orders!B:B,A64,orders!F:F) -> 71.62 | H64: =COUNTIF(orders!B:B,A64) -> 2 | I64: =IF(H64>1,"Repeat Customer","One-Time Customer") -> Repeat Customer
A65: CUST00064 | B65: bake.harper@bigpond.com.au | C65: Harper | D65: Turner | E65: Perth | F65: WA | G65: =SUMIF(orders!B:B,A65,orders!F:F) -> 960.97 | H65: =COUNTIF(orders!B:B,A65) -> 11 | I65: =IF(H65>1,"Repeat Customer","One-Time Customer") -> Repeat Customer
A66: CUST00065 | B66: grace.art@gmail.com | C66: Gina | D66: Queen | E66: Kalgoorlie | F66: WA | G66: =SUMIF(orders!B:B,A66,orders!F:F) -> 652.21 | H66: =COUNTIF(orders!B:B,A66) -> 7 | I66: =IF(H66>1,"Repeat Customer","One-Time Customer") -> Repeat Customer
A67: CUST00066 | B67: coastalleilani@yahoo.com | C67: Leilani | D67: Kowalski | E67: Albany | F67: WA | G67: =SUMIF(orders!B:B,A67,orders!F:F) -> 151.1 | H67: =COUNTIF(orders!B:B,A67) -> 2 | I67: =IF(H67>1,"Repeat Customer","One-Time Customer") -> Repeat Customer | M67: NSW represents CompradaRoo's largest customer base and highest total revenue, while Victorian customers have the highest average spend per customer, indicating a particularly valuable market segment.
A68: CUST00067 | B68: olivertran@microsoft.com | C68: Oliver | D68: Tran | E68: Toowoomba | F68: QLD | G68: =SUMIF(orders!B:B,A68,orders!F:F) -> 0 | H68: =COUNTIF(orders!B:B,A68) -> 0 | I68: =IF(H68>1,"Repeat Customer","One-Time Customer") -> One-Time Customer
A69: CUST00068 | B69: harper_166@gmail.com | C69: Harper | D69: Smith | E69: Melbourne | F69: VIC | G69: =SUMIF(orders!B:B,A69,orders!F:F) -> 0 | H69: =COUNTIF(orders!B:B,A69) -> 0 | I69: =IF(H69>1,"Repeat Customer","One-Time Customer") -> One-Time Customer
A70: CUST00069 | B70: lateliam@aol.com | C70: Liam | D70: Murphy | E70: Adelaide | F70: SA | G70: =SUMIF(orders!B:B,A70,orders!F:F) -> 0 | H70: =COUNTIF(orders!B:B,A70) -> 0 | I70: =IF(H70>1,"Repeat Customer","One-Time Customer") -> One-Time Customer | M70: 32% of customers are repeat customers (141 out of 441)
A71: CUST00070 | B71: walker.alex@yahoo.com | C71: Alexander | D71: Walker | E71: Melbourne | F71: VIC | G71: =SUMIF(orders!B:B,A71,orders!F:F) -> 202.91 | H71: =COUNTIF(orders!B:B,A71) -> 2 | I71: =IF(H71>1,"Repeat Customer","One-Time Customer") -> Repeat Customer | M71: 85% of revenue comes from repeat customers (32,198.86 out of 37,823.54)
A72: CUST00071 | B72: johnson.archie@optusnet.com.au | C72: Archie | D72: Johnson | E72: Cairns | F72: QLD | G72: =SUMIF(orders!B:B,A72,orders!F:F) -> 0 | H72: =COUNTIF(orders!B:B,A72) -> 0 | I72: =IF(H72>1,"Repeat Customer","One-Time Customer") -> One-Time Customer
A73: CUST00072 | B73: avawild@hotmail.com | C73: Ava | D73: Taylor | E73: Sydney | F73: NSW | G73: =SUMIF(orders!B:B,A73,orders!F:F) -> 0 | H73: =COUNTIF(orders!B:B,A73) -> 0 | I73: =IF(H73>1,"Repeat Customer","One-Time Customer") -> One-Time Customer
A74: CUST00073 | B74: graceearly@bigpond.com.au | C74: Grant | D74: Walker | E74: Hervey Bay | F74: QLD | G74: =SUMIF(orders!B:B,A74,orders!F:F) -> 0 | H74: =COUNTIF(orders!B:B,A74) -> 0 | I74: =IF(H74>1,"Repeat Customer","One-Time Customer") -> One-Time Customer
A75: CUST00074 | B75: costa.zoe@gmail.com | C75: Zoe | D75: Costa | E75: Mildura | F75: VIC | G75: =SUMIF(orders!B:B,A75,orders!F:F) -> 174.34 | H75: =COUNTIF(orders!B:B,A75) -> 3 | I75: =IF(H75>1,"Repeat Customer","One-Time Customer") -> Repeat Customer
A76: CUST00075 | B76: georgia.kaur@bigpond.com.au | C76: Georgia | D76: Kaur | E76: Mildura | F76: VIC | G76: =SUMIF(orders!B:B,A76,orders!F:F) -> 0 | H76: =COUNTIF(orders!B:B,A76) -> 0 | I76: =IF(H76>1,"Repeat Customer","One-Time Customer") -> One-Time Customer
A77: CUST00076 | B77: zoe96@gmail.com | C77: Flo | D77: Turner | E77: Melbourne | F77: VIC | G77: =SUMIF(orders!B:B,A77,orders!F:F) -> 62.02 | H77: =COUNTIF(orders!B:B,A77) -> 2 | I77: =IF(H77>1,"Repeat Customer","One-Time Customer") -> Repeat Customer
A78: CUST00077 | B78: samuel1981@optusnet.com.au | C78: Samuel | D78: Kowalski | E78: Torquay | F78: VIC | G78: =SUMIF(orders!B:B,A78,orders!F:F) -> 0 | H78: =COUNTIF(orders!B:B,A78) -> 0 | I78: =IF(H78>1,"Repeat Customer","One-Time Customer") -> One-Time Customer
A79: CUST00078 | B79: freyacoastal@live.au | C79: Freya | D79: Kelly | E79: Gold Coast | F79: QLD | G79: =SUMIF(orders!B:B,A79,orders!F:F) -> 0 | H79: =COUNTIF(orders!B:B,A79) -> 0 | I79: =IF(H79>1,"Repeat Customer","One-Time Customer") -> One-Time Customer
A80: CUST00079 | B80: ruby49@gmail.com | C80: Ruby | D80: Murphy | E80: Ballarat | F80: VIC | G80: =SUMIF(orders!B:B,A80,orders!F:F) -> 143.62 | H80: =COUNTIF(orders!B:B,A80) -> 2 | I80: =IF(H80>1,"Repeat Customer","One-Time Customer") -> Repeat Customer
A81: CUST00080 | B81: henry.sato@microsoft.com | C81: Henry | D81: Sato | E81: Melbourne | F81: VIC | G81: =SUMIF(orders!B:B,A81,orders!F:F) -> 231.88 | H81: =COUNTIF(orders!B:B,A81) -> 3 | I81: =IF(H81>1,"Repeat Customer","One-Time Customer") -> Repeat Customer
A82: CUST00081 | B82: tthompson@yahoo.com | C82: Thomas | D82: Thompson | E82: Toowoomba | F82: QLD | G82: =SUMIF(orders!B:B,A82,orders!F:F) -> 255.49 | H82: =COUNTIF(orders!B:B,A82) -> 3 | I82: =IF(H82>1,"Repeat Customer","One-Time Customer") -> Repeat Customer
A83: CUST00082 | B83: charlie30@bigpond.com.au | C83: Charlotte | D83: Williams | E83: Hobart | F83: TAS | G83: =SUMIF(orders!B:B,A83,orders!F:F) -> 66.02 | H83: =COUNTIF(orders!B:B,A83) -> 2 | I83: =IF(H83>1,"Repeat Customer","One-Time Customer") -> Repeat Customer
... A442: CUST00441 | B442: art.ella@bigpond.com.au | C442: Ella | D442: Nowak | E442: Toowoomba | F442: QLD | G442: =SUMIF(orders!B:B,A442,orders!F:F) -> 0 | H442: =COUNTIF(orders!B:B,A442) -> 0 | I442: =IF(H442>1,"Repeat Customer","One-Time Customer") -> One-Time Customer

Sheet orders
A1: order_id | B1: customer_id | C1: order_date | D1: delivery_est | E1: delivery_date | F1: order_total_aud | G1: delivery_delay | H1: Delivery_time_all | I1: Delay (-)/On time (+)_all
A2: ORD000001 | B2: CUST00004 | C2: 45322.508 | D2: 45333 | E2: 45333.673 | F2: 18.74 | G2: =INT(E2)-INT(D2) -> 0 | H2: 11.16515 | I2: -0.67280093 | L2: =SUM(F2:F166) -> 12430.73 | M2: =SUM(N267) -> 0
A3: ORD000002 | B3: CUST00005 | C3: 45323.16 | D3: 45329 | E3: 45329.696 | F3: 35.97 | G3: =INT(E3)-INT(D3) -> 0 | H3: 6.5360417 | I3: -0.69615741
A4: ORD000003 | B4: CUST00011 | C4: 45342.849 | D4: 45347 | E4: 45347.548 | F4: 23.96 | G4: =INT(E4)-INT(D4) -> 0 | H4: 4.6990046 | I4: -0.54798611
A5: ORD000004 | B5: CUST00015 | C5: 45355.067 | D5: 45359 | E5: 45361.396 | F5: 36.25 | G5: =INT(E5)-INT(D5) -> 2 | H5: 6.329375 | I5: -2.3961921
A6: ORD000005 | B6: CUST00017 | C6: 45356.483 | D6: 45358 | E6: 45358.605 | F6: 7.18 | G6: =INT(E6)-INT(D6) -> 0 | H6: 2.1217361 | I6: -0.6046412
A7: ORD000006 | B7: CUST00016 | C7: 45358.174 | D7: 45363 | E7: 45363.656 | F7: 46.28 | G7: =INT(E7)-INT(D7) -> 0 | H7: 5.4815394 | I7: -0.65565972
A8: ORD000007 | B8: CUST00018 | C8: 45363.414 | D8: 45367 | E8: 45367.344 | F8: 31.78 | G8: =INT(E8)-INT(D8) -> 0 | H8: 3.9304745 | I8: -0.34443287
A9: ORD000008 | B9: CUST00022 | C9: 45376.197 | D9: 45381 | E9: 45382.512 | F9: 20.2 | G9: =INT(E9)-INT(D9) -> 1 | H9: 6.3154514 | I9: -1.5124074
A10: ORD000009 | B10: CUST00024 | C10: 45378.181 | D10: 45386 | E10: 45386.642 | F10: 26.37 | G10: =INT(E10)-INT(D10) -> 0 | H10: 8.4615856 | I10: -0.64234954
A11: ORD000010 | B11: CUST00028 | C11: 45384.319 | D11: 45389 | E11: 45389.655 | F11: 45.78 | G11: =INT(E11)-INT(D11) -> 0 | H11: 5.3359606 | I11: -0.65525463
A12: ORD000011 | B12: CUST00029 | C12: 45385.5 | D12: 45393 | E12: 45391.604 | F12: 104.6 | G12: =INT(E12)-INT(D12) -> -2 | H12: 6.1044444 | I12: 1.3960069
A13: ORD000012 | B13: CUST00025 | C13: 45387.401 | D13: 45397 | E13: 45396.668 | F13: 48.67 | G13: =INT(E13)-INT(D13) -> -1 | H13: 9.267037 | I13: 0.33194444
A14: ORD000013 | B14: CUST00034 | C14: 45388.231 | D14: 45392 | E14: 45391.5 | F14: 37.94 | G14: =INT(E14)-INT(D14) -> -1 | H14: 3.2688657 | I14: 0.50025463
... A48: ORD000047 | B48: CUST00115 | C48: 45448.593 | D48: 45456 | E48: 45456.378 | F48: 37.81 | G48: =INT(E48)-INT(D48) -> 0 | H48: 7.7851389 | I48: -0.37793982
A49: ORD000048 | B49: CUST00117 | C49: 45449.566 | D49: 45455 | E49: 45456.517 | F49: 70.28 | G49: =INT(E49)-INT(D49) -> 1 | H49: 6.9510185 | I49: -1.5169907 | P49: =SUM(F2:F479) -> 37823.54
A50: ORD000049 | B50: CUST00119 | C50: 45450.026 | D50: 45454 | E50: 45457.595 | F50: 10.02 | G50: =INT(E50)-INT(D50) -> 3 | H50: 7.5689005 | I50: -3.5948727
A51: ORD000050 | B51: CUST00120 | C51: 45450.611 | D51: 45455 | E51: 45454.74 | F51: 37.43 | G51: =INT(E51)-INT(D51) -> -1 | H51: 4.129294 | I51: 0.25986111
A52: ORD000051 | B52: CUST00121 | C52: 45452.31 | D52: 45460 | E52: 45459.485 | F52: 119.27 | G52: =INT(E52)-INT(D52) -> -1 | H52: 7.1742014 | I52: 0.51542824
A53: ORD000052 | B53: CUST00028 | C53: 45452.406 | D53: 45462 | E53: 45464.64 | F53: 16.14 | G53: =INT(E53)-INT(D53) -> 2 | H53: 12.233808 | I53: -2.639537
A54: ORD000053 | B54: CUST00124 | C54: 45453.395 | D54: 45463 | E54: 45464.685 | F54: 46.84 | G54: =INT(E54)-INT(D54) -> 1 | H54: 11.289687 | I54: -1.6849884
A55: ORD000054 | B55: CUST00130 | C55: 45458.6 | D55: 45467 | E55: 45466.363 | F55: 4.94 | G55: =INT(E55)-INT(D55) -> -1 | H55: 7.7630556 | I55: 0.63741898
A56: ORD000055 | B56: CUST00131 | C56: 45458.936 | D56: 45466 | E56: 45466.455 | F56: 126.9 | G56: =INT(E56)-INT(D56) -> 0 | H56: 7.5184722 | I56: -0.45475694
A57: ORD000056 | B57: CUST00132 | C57: 45458.954 | D57: 45465 | E57: 45467.545 | F57: 155.05 | G57: =INT(E57)-INT(D57) -> 2 | H57: 8.5906134 | I57: -2.5445602
A58: ORD000057 | B58: CUST00133 | C58: 45460.714 | D58: 45467 | E58: 45467.606 | F58: 117.5 | G58: =INT(E58)-INT(D58) -> 0 | H58: 6.8927083 | I58: -0.60638889
A59: ORD000058 | B59: CUST00137 | C59: 45462.761 | D59: 45467 | E59: 45467.646 | F59: 18.99 | G59: =INT(E59)-INT(D59) -> 0 | H59: 4.8852778 | I59: -0.64601852
A60: ORD000059 | B60: CUST00089 | C60: 45463.543 | D60: 45473 | E60: 45474.636 | F60: 85.13 | G60: =INT(E60)-INT(D60) -> 1 | H60: 11.092778 | I60: -1.6360069
A61: ORD000060 | B61: CUST00138 | C61: 45464.223 | D61: 45471 | E61: 45472.663 | F61: 86.28 | G61: =INT(E61)-INT(D61) -> 1 | H61: 8.4403819 | I61: -1.6633796
... A134: ORD000133 | B134: CUST00233 | C134: 45634.624 | D134: 45639 | E134: 45641.511 | F134: 23.12 | G134: =INT(E134)-INT(D134) -> 2 | H134: 6.8870139 | I134: -2.5113657
A135: ORD000134 | B135: CUST00011 | C135: 45635.1 | D135: 45643 | E135: 45643.667 | F135: 105.72 | G135: =INT(E135)-INT(D135) -> 0 | H135: 8.5672685 | I135: -0.66737269 | L135: =AVERAGE(F2:F166) -> 75.337758
A136: ORD000135 | B136: CUST00235 | C136: 45635.411 | D136: 45641 | E136: 45641.44 | F136: 63.79 | G136: =INT(E136)-INT(D136) -> 0 | H136: 6.0287153 | I136: -0.44009259
A137: ORD000136 | B137: CUST00202 | C137: 45635.542 | D137: 45642 | E137: 45643.444 | F137: 171.34 | G137: =INT(E137)-INT(D137) -> 1 | H137: 7.9027778 | I137: -1.4444329 | L137: avergae of 25
A138: ORD000137 | B138: CUST00237 | C138: 45637.409 | D138: 45642 | E138: 45644.353 | F138: 80.95 | G138: =INT(E138)-INT(D138) -> 2 | H138: 6.9446065 | I138: -2.3531944
A139: ORD000138 | B139: CUST00240 | C139: 45638.015 | D139: 45644 | E139: 45644.719 | F139: 97.18 | G139: =INT(E139)-INT(D139) -> 0 | H139: 6.7041782 | I139: -0.71912037
A140: ORD000139 | B140: CUST00242 | C140: 45638.34 | D140: 45643 | E140: 45643.424 | F140: 27.18 | G140: =INT(E140)-INT(D140) -> 0 | H140: 5.0832523 | I140: -0.42366898
A141: ORD000140 | B141: CUST00241 | C141: 45638.611 | D141: 45644 | E141: 45644.453 | F141: 91.22 | G141: =INT(E141)-INT(D141) -> 0 | H141: 5.8422917 | I141: -0.45326389
A142: ORD000141 | B142: CUST00081 | C142: 45639.339 | D142: 45643 | E142: 45642.667 | F142: 53.83 | G142: =INT(E142)-INT(D142) -> -1 | H142: 3.3281481 | I142: 0.33284722
A143: ORD000142 | B143: CUST00170 | C143: 45639.975 | D143: 45644 | E143: 45644.423 | F143: 50.45 | G143: =INT(E143)-INT(D143) -> 0 | H143: 4.4484722 | I143: -0.42299769
A144: ORD000143 | B144: CUST00240 | C144: 45642.911 | D144: 45649 | E144: 45648.736 | F144: 78.15 | G144: =INT(E144)-INT(D144) -> -1 | H144: 5.8254745 | I144: 0.26383102
A145: ORD000144 | B145: CUST00037 | C145: 45642.931 | D145: 45649 | E145: 45653.385 | F145: 232.38 | G145: =INT(E145)-INT(D145) -> 4 | H145: 10.453403 | I145: -4.3846065
A146: ORD000145 | B146: CUST00011 | C146: 45643.381 | D146: 45653 | E146: 45653.588 | F146: 159.54 | G146: =INT(E146)-INT(D146) -> 0 | H146: 10.207384 | I146: -0.58819444
A147: ORD000146 | B147: CUST00223 | C147: 45645.145 | D147: 45653 | E147: 45653.609 | F147: 68.97 | G147: =INT(E147)-INT(D147) -> 0 | H147: 8.4645139 | I147: -0.6093287
A148: ORD000147 | B148: CUST00032 | C148: 45646.379 | D148: 45654 | E148: 45656.385 | F148: 102.86 | G148: =INT(E148)-INT(D148) -> 2 | H148: 10.006412 | I148: -2.3853009
A149: ORD000148 | B149: CUST00250 | C149: 45646.58 | D149: 45656 | E149: 45661.529 | F149: 185.82 | G149: =INT(E149)-INT(D149) -> 5 | H149: 14.948681 | I149: -5.528588
... A166: ORD000165 | B166: CUST00264 | C166: 45657.368 | D166: 45664 | E166: 45663.721 | F166: 152.68 | G166: =INT(E166)-INT(D166) -> -1 | H166: 6.3533796 | I166: 0.27856482
A167: ORD000166 | B167: CUST00270 | C167: 45660.309 | D167: 45662 | E167: 45661.623 | F167: 25.6 | G167: =INT(E167)-INT(D167) -> -1 | H167: 1.3143403 | I167: 0.37694444 | L167: =AVERAGE(F167:F417) -> 81.915618
A168: ORD000167 | B168: CUST00006 | C168: 45669.389 | D168: 45677 | E168: 45679.359 | F168: 14.97 | G168: =INT(E168)-INT(D168) -> 2 | H168: 9.9701852 | I168: -2.3591667
A169: ORD000168 | B169: CUST00230 | C169: 45671.236 | D169: 45674 | E169: 45673.738 | F169: 32.39 | G169: =INT(E169)-INT(D169) -> -1 | H169: 2.5017593 | I169: 0.26226852
A170: ORD000169 | B170: CUST00010 | C170: 45675.211 | D170: 45679 | E170: 45678.608 | F170: 13.34 | G170: =INT(E170)-INT(D170) -> -1 | H170: 3.3964005 | I170: 0.39231481
A171: ORD000170 | B171: CUST00033 | C171: 45683.504 | D171: 45689 | E171: 45693.472 | F171: 53.99 | G171: =INT(E171)-INT(D171) -> 4 | H171: 9.9683102 | I171: -4.4722801
A172: ORD000171 | B172: CUST00041 | C172: 45688.778 | D172: 45697 | E172: 45697.415 | F172: 117.05 | G172: =INT(E172)-INT(D172) -> 0 | H172: 8.6361806 | I172: -0.41452546
A173: ORD000172 | B173: CUST00276 | C173: 45689.416 | D173: 45698 | E173: 45698.541 | F173: 87.68 | G173: =INT(E173)-INT(D173) -> 0 | H173: 9.1252778 | I173: -0.54146991
A174: ORD000173 | B174: CUST00191 | C174: 45691.453 | D174: 45697 | E174: 45696.556 | F174: 245.61 | G174: =INT(E174)-INT(D174) -> -1 | H174: 5.1020486 | I174: 0.44449074
A175: ORD000174 | B175: CUST00195 | C175: 45693.406 | D175: 45703 | E175: 45703.529 | F175: 32.16 | G175: =INT(E175)-INT(D175) -> 0 | H175: 10.12235 | I175: -0.52859954
A176: ORD000175 | B176: CUST00161 | C176: 45703.163 | D176: 45706 | E176: 45707.358 | F176: 68.77 | G176: =INT(E176)-INT(D176) -> 1 | H176: 4.1953588 | I176: -1.3584259
A177: ORD000176 | B177: CUST00035 | C177: 45709.391 | D177: 45714 | E177: 45715.425 | F177: 58.42 | G177: =INT(E177)-INT(D177) -> 1 | H177: 6.0347222 | I177: -1.4254977
A178: ORD000177 | B178: CUST00084 | C178: 45709.53 | D178: 45714 | E178: 45714.505 | F178: 95.13 | G178: =INT(E178)-INT(D178) -> 0 | H178: 4.9743056 | I178: -0.50475694
A179: ORD000178 | B179: CUST00165 | C179: 45709.639 | D179: 45712 | E179: 45711.671 | F179: 57.56 | G179: =INT(E179)-INT(D179) -> -1 | H179: 2.0317593 | I179: 0.32934028
... A265: ORD000264 | B265: CUST00329 | C265: 45831.646 | D265: 45837 | E265: 45837.592 | F265: 23 | G265: =INT(E265)-INT(D265) -> 0 | H265: 5.9463194 | I265: -0.59230324
A266: ORD000265 | B266: CUST00352 | C266: 45837.771 | D266: 45844 | E266: 45843.424 | F266: 77.21 | G266: =INT(E266)-INT(D266) -> -1 | H266: 5.6528588 | I266: 0.57582176 | N266: =_xleta.SUM -> #VALUE!
A267: ORD000266 | B267: CUST00302 | C267: 45841.081 | D267: 45846 | E267: 45848.725 | F267: 37.05 | G267: =INT(E267)-INT(D267) -> 2 | H267: 7.6435185 | I267: -2.7248264
A268: ORD000267 | B268: CUST00026 | C268: 45841.238 | D268: 45843 | E268: 45843.678 | F268: 13.72 | G268: =INT(E268)-INT(D268) -> 0 | H268: 2.440625 | I268: -0.67826389
A269: ORD000268 | B269: CUST00355 | C269: 45841.44 | D269: 45849 | E269: 45849.603 | F269: 68.71 | G269: =INT(E269)-INT(D269) -> 0 | H269: 8.162963 | I269: -0.60318287
A270: ORD000269 | B270: CUST00190 | C270: 45842.077 | D270: 45850 | E270: 45850.54 | F270: 108.48 | G270: =INT(E270)-INT(D270) -> 0 | H270: 8.4622454 | I270: -0.53967593
A271: ORD000270 | B271: CUST00260 | C271: 45842.687 | D271: 45850 | E271: 45851.612 | F271: 46.85 | G271: =INT(E271)-INT(D271) -> 1 | H271: 8.925544 | I271: -1.6122106
A272: ORD000271 | B272: CUST00133 | C272: 45843.528 | D272: 45849 | E272: 45851.494 | F272: 13.94 | G272: =INT(E272)-INT(D272) -> 2 | H272: 7.9658449 | I272: -2.493669
A273: ORD000272 | B273: CUST00010 | C273: 45843.874 | D273: 45846 | E273: 45846.689 | F273: 247.75 | G273: =INT(E273)-INT(D273) -> 0 | H273: 2.8151389 | I273: -0.68900463
A274: ORD000273 | B274: CUST00341 | C274: 45845.506 | D274: 45852 | E274: 45852.364 | F274: 222.5 | G274: =INT(E274)-INT(D274) -> 0 | H274: 6.8584722 | I274: -0.36428241
A275: ORD000274 | B275: CUST00155 | C275: 45846.698 | D275: 45850 | E275: 45851.483 | F275: 0 | G275: =INT(E275)-INT(D275) -> 1 | H275: 4.7852315 | I275: -1.4829977
A276: ORD000275 | B276: CUST00052 | C276: 45846.946 | D276: 45852 | E276: 45851.471 | F276: 43.68 | G276: =INT(E276)-INT(D276) -> -1 | H276: 4.5250231 | I276: 0.52866898
A277: ORD000276 | B277: CUST00153 | C277: 45847.378 | D277: 45851 | E277: 45851.546 | F277: 83.98 | G277: =INT(E277)-INT(D277) -> 0 | H277: 4.1687616 | I277: -0.5462963
A278: ORD000277 | B278: CUST00030 | C278: 45847.999 | D278: 45852 | E278: 45852.461 | F278: 50.71 | G278: =INT(E278)-INT(D278) -> 0 | H278: 4.4625463 | I278: -0.46135417
... A417: ORD000416 | B417: CUST00336 | C417: 46022.836 | D417: 46024 | E417: 46025.363 | F417: 29.07 | G417: =INT(E417)-INT(D417) -> 1 | H417: 2.5264005 | I417: -1.362662
A418: ORD000417 | B418: CUST00042 | C418: 46026.12 | D418: 46032 | E418: 46031.364 | F418: 32.32 | G418: =INT(E418)-INT(D418) -> -1 | H418: 5.2441782 | I418: 0.63552083 | L418: =AVERAGE(F418:F479) -> 77.935323
A419: ORD000418 | B419: CUST00340 | C419: 46027.074 | D419: 46034 | E419: 46033.443 | F419: 32.09 | G419: =INT(E419)-INT(D419) -> -1 | H419: 6.3682986 | I419: 0.55721065
A420: ORD000419 | B420: CUST00058 | C420: 46031.309 | D420: 46036 | E420: 46036.4 | F420: 54.51 | G420: =INT(E420)-INT(D420) -> 0 | H420: 5.0912153 | I420: -0.40015046
A421: ORD000420 | B421: CUST00126 | C421: 46031.533 | D421: 46038 | E421: 46039.374 | F421: 53.75 | G421: =INT(E421)-INT(D421) -> 1 | H421: 7.8412616 | I421: -1.3737963
A422: ORD000421 | B422: CUST00192 | C422: 46035.628 | D422: 46043 | E422: 46044.6 | F422: 9.97 | G422: =INT(E422)-INT(D422) -> 1 | H422: 8.9717824 | I422: -1.5995718
A423: ORD000422 | B423: CUST00015 | C423: 46039.212 | D423: 46042 | E423: 46043.414 | F423: 14.9 | G423: =INT(E423)-INT(D423) -> 1 | H423: 4.2020949 | I423: -1.4144329
A424: ORD000423 | B424: CUST00335 | C424: 46044.163 | D424: 46048 | E424: 46046.628 | F424: 0 | G424: =INT(E424)-INT(D424) -> -2 | H424: 2.4643519 | I424: 1.3723495
A425: ORD000424 | B425: CUST00426 | C425: 46045.027 | D425: 46051 | E425: 46051.543 | F425: 11.92 | G425: =INT(E425)-INT(D425) -> 0 | H425: 6.5156019 | I425: -0.54289352
A426: ORD000425 | B426: CUST00373 | C426: 46048.085 | D426: 46051 | E426: 46051.508 | F426: 40.62 | G426: =INT(E426)-INT(D426) -> 0 | H426: 3.4228009 | I426: -0.50825232
A427: ORD000426 | B427: CUST00428 | C427: 46050.348 | D427: 46060 | E427: 46060.579 | F427: 24.27 | G427: =INT(E427)-INT(D427) -> 0 | H427: 10.231771 | I427: -0.57938657
A428: ORD000427 | B428: CUST00166 | C428: 46065.297 | D428: 46070 | E428: 46069.507 | F428: 47 | G428: =INT(E428)-INT(D428) -> -1 | H428: 4.2095949 | I428: 0.49299769
A429: ORD000428 | B429: CUST00237 | C429: 46068.009 | D429: 46076 | E429: 46075.369 | F429: 5.09 | G429: =INT(E429)-INT(D429) -> -1 | H429: 7.3592708 | I429: 0.63149306
A430: ORD000429 | B430: CUST00074 | C430: 46073.226 | D430: 46080 | E430: 46085.431 | F430: 48.57 | G430: =INT(E430)-INT(D430) -> 5 | H430: 12.20515 | I430: -5.4313079
... A479: ORD000478 | B479: CUST00416 | C479: 46112.512 | D479: 46122 | E479: 46123.425 | F479: 116.19 | G479: =INT(E479)-INT(D479) -> 1 | H479: 10.912396 | I479: -1.4247917
F480: =SUM(F2:F479) -> 37823.54 | G480: =ROUND(AVERAGE(G2:G479),2) -> 0.37
F481: =AVERAGE(F2:F479) -> 79.128745

Sheet order_items
A1: order_id | B1: product_id | C1: product_quantity | D1: product_category | E1: product_price | F1: item_revenue | G1: product_name | H1: seller_id | I1: seller_state | J1: seller_user
A2: ORD000001 | B2: PROD00077 | C2: 1 | D2: =_xlfn.XLOOKUP(order_items!B2,products_2026!A:A,products_2026!C:C,,0,) -> Home | E2: =_xlfn.XLOOKUP(B2,products_2026!A:A,products_2026!D:D,,0,) -> 26.76 | F2: =C2*E2 -> 26.76 | G2: =_xlfn.XLOOKUP(B2,products_2026!A:A,products_2026!B:B,,0,) -> Scented Drawer Sachets Jasmine | H2: =_xlfn.XLOOKUP(B2,products_2026!A:A,products_2026!E:E,,0,) -> SELL0036 | I2: =IFERROR(_xlfn.XLOOKUP(H2,sellers_2026!A:A,sellers_2026!G:G,,0,), "unknown/inactive") -> NT | J2: =_xlfn.XLOOKUP(H2,sellers_2026!A:A,sellers_2026!B:B,,0,) -> goodqualityemporium
A3: ORD000002 | B3: PROD00191 | C3: 1 | D3: =_xlfn.XLOOKUP(order_items!B3,products_2026!A:A,products_2026!C:C,,0,) -> Jewellery | E3: =_xlfn.XLOOKUP(B3,products_2026!A:A,products_2026!D:D,,0,) -> 47.32 | F3: =C3*E3 -> 47.32 | G3: =_xlfn.XLOOKUP(B3,products_2026!A:A,products_2026!B:B,,0,) -> Men’s Leather Band Bracelet | H3: =_xlfn.XLOOKUP(B3,products_2026!A:A,products_2026!E:E,,0,) -> SELL0062 | I3: =IFERROR(_xlfn.XLOOKUP(H3,sellers_2026!A:A,sellers_2026!G:G,,0,), "unknown/inactive") -> QLD | J3: =_xlfn.XLOOKUP(H3,sellers_2026!A:A,sellers_2026!B:B,,0,) -> queenslandqweenie
A4: ORD000003 | B4: PROD00230 | C4: 1 | D4: =_xlfn.XLOOKUP(order_items!B4,products_2026!A:A,products_2026!C:C,,0,) -> Beauty | E4: =_xlfn.XLOOKUP(B4,products_2026!A:A,products_2026!D:D,,0,) -> 25 | F4: =C4*E4 -> 25 | G4: =_xlfn.XLOOKUP(B4,products_2026!A:A,products_2026!B:B,,0,) -> Face mask peel-off orange 3 pack | H4: =_xlfn.XLOOKUP(B4,products_2026!A:A,products_2026!E:E,,0,) -> SELL0075 | I4: =IFERROR(_xlfn.XLOOKUP(H4,sellers_2026!A:A,sellers_2026!G:G,,0,), "unknown/inactive") -> NSW | J4: =_xlfn.XLOOKUP(H4,sellers_2026!A:A,sellers_2026!B:B,,0,) -> nhlay6j49a
A5: ORD000004 | B5: PROD00204 | C5: 1 | D5: =_xlfn.XLOOKUP(order_items!B5,products_2026!A:A,products_2026!C:C,,0,) -> Electronics | E5: =_xlfn.XLOOKUP(B5,products_2026!A:A,products_2026!D:D,,0,) -> 38.56 | F5: =C5*E5 -> 38.56 | G5: =_xlfn.XLOOKUP(B5,products_2026!A:A,products_2026!B:B,,0,) -> USB C Fast Charger 30W (Black) | H5: =_xlfn.XLOOKUP(B5,products_2026!A:A,products_2026!E:E,,0,) -> SELL0067 | I5: =IFERROR(_xlfn.XLOOKUP(H5,sellers_2026!A:A,sellers_2026!G:G,,0,), "unknown/inactive") -> WA | J5: =_xlfn.XLOOKUP(H5,sellers_2026!A:A,sellers_2026!B:B,,0,) -> w71bv3mee1
A6: ORD000005 | B6: PROD00452 | C6: 1 | D6: =_xlfn.XLOOKUP(order_items!B6,products_2026!A:A,products_2026!C:C,,0,) -> Stationery | E6: =_xlfn.XLOOKUP(B6,products_2026!A:A,products_2026!D:D,,0,) -> 7.32 | F6: =C6*E6 -> 7.32 | G6: =_xlfn.XLOOKUP(B6,products_2026!A:A,products_2026!B:B,,0,) -> Gel Pen Set - 10 pack (Black) | H6: =_xlfn.XLOOKUP(B6,products_2026!A:A,products_2026!E:E,,0,) -> SELL0010 | I6: =IFERROR(_xlfn.XLOOKUP(H6,sellers_2026!A:A,sellers_2026!G:G,,0,), "unknown/inactive") -> VIC | J6: =_xlfn.XLOOKUP(H6,sellers_2026!A:A,sellers_2026!B:B,,0,) -> hobbylobby
A7: ORD000006 | B7: PROD00084 | C7: 1 | D7: =_xlfn.XLOOKUP(order_items!B7,products_2026!A:A,products_2026!C:C,,0,) -> Home | E7: =_xlfn.XLOOKUP(B7,products_2026!A:A,products_2026!D:D,,0,) -> 46.55 | F7: =C7*E7 -> 46.55 | G7: =_xlfn.XLOOKUP(B7,products_2026!A:A,products_2026!B:B,,0,) -> Stainless Steel Cutting Board | H7: =_xlfn.XLOOKUP(B7,products_2026!A:A,products_2026!E:E,,0,) -> SELL0037 | I7: =IFERROR(_xlfn.XLOOKUP(H7,sellers_2026!A:A,sellers_2026!G:G,,0,), "unknown/inactive") -> VIC | J7: =_xlfn.XLOOKUP(H7,sellers_2026!A:A,sellers_2026!B:B,,0,) -> storeshop
A8: ORD000007 | B8: PROD00283 | C8: 1 | D8: =_xlfn.XLOOKUP(order_items!B8,products_2026!A:A,products_2026!C:C,,0,) -> Clothes | E8: =_xlfn.XLOOKUP(B8,products_2026!A:A,products_2026!D:D,,0,) -> 32.76 | F8: =C8*E8 -> 32.76 | G8: =_xlfn.XLOOKUP(B8,products_2026!A:A,products_2026!B:B,,0,) -> Kids Cotton Pyjamas 6-8y | H8: =_xlfn.XLOOKUP(B8,products_2026!A:A,products_2026!E:E,,0,) -> SELL0086 | I8: =IFERROR(_xlfn.XLOOKUP(H8,sellers_2026!A:A,sellers_2026!G:G,,0,), "unknown/inactive") -> VIC | J8: =_xlfn.XLOOKUP(H8,sellers_2026!A:A,sellers_2026!B:B,,0,) -> clothesforlife | L8: Row Labels | M8: Sum of item_revenue
A9: ORD000008 | B9: PROD00081 | C9: 1 | D9: =_xlfn.XLOOKUP(order_items!B9,products_2026!A:A,products_2026!C:C,,0,) -> Jewellery | E9: =_xlfn.XLOOKUP(B9,products_2026!A:A,products_2026!D:D,,0,) -> 20.59 | F9: =C9*E9 -> 20.59 | G9: =_xlfn.XLOOKUP(B9,products_2026!A:A,products_2026!B:B,,0,) -> Crystal Drop Earrings Clipon | H9: =_xlfn.XLOOKUP(B9,products_2026!A:A,products_2026!E:E,,0,) -> SELL0037 | I9: =IFERROR(_xlfn.XLOOKUP(H9,sellers_2026!A:A,sellers_2026!G:G,,0,), "unknown/inactive") -> VIC | J9: =_xlfn.XLOOKUP(H9,sellers_2026!A:A,sellers_2026!B:B,,0,) -> storeshop | L9: Outdoor | M9: 16526.25
A10: ORD000009 | B10: PROD00171 | C10: 1 | D10: =_xlfn.XLOOKUP(order_items!B10,products_2026!A:A,products_2026!C:C,,0,) -> Clothes | E10: =_xlfn.XLOOKUP(B10,products_2026!A:A,products_2026!D:D,,0,) -> 40.28 | F10: =C10*E10 -> 40.28 | G10: =_xlfn.XLOOKUP(B10,products_2026!A:A,products_2026!B:B,,0,) -> Men’s Chino Shorts S | H10: =_xlfn.XLOOKUP(B10,products_2026!A:A,products_2026!E:E,,0,) -> SELL0058 | I10: =IFERROR(_xlfn.XLOOKUP(H10,sellers_2026!A:A,sellers_2026!G:G,,0,), "unknown/inactive") -> QLD | J10: =_xlfn.XLOOKUP(H10,sellers_2026!A:A,sellers_2026!B:B,,0,) -> au6ynzdcy5 | L10: Home | M10: 6457.93
A11: ORD000010 | B11: PROD00240 | C11: 1 | D11: =_xlfn.XLOOKUP(order_items!B11,products_2026!A:A,products_2026!C:C,,0,) -> Outdoor | E11: =_xlfn.XLOOKUP(B11,products_2026!A:A,products_2026!D:D,,0,) -> 51.74 | F11: =C11*E11 -> 51.74 | G11: =_xlfn.XLOOKUP(B11,products_2026!A:A,products_2026!B:B,,0,) -> Garden Ornament Frog | H11: =_xlfn.XLOOKUP(B11,products_2026!A:A,products_2026!E:E,,0,) -> SELL0077 | I11: =IFERROR(_xlfn.XLOOKUP(H11,sellers_2026!A:A,sellers_2026!G:G,,0,), "unknown/inactive") -> ACT | J11: =_xlfn.XLOOKUP(H11,sellers_2026!A:A,sellers_2026!B:B,,0,) -> doorsyout | L11: Electronics | M11: 4385.23
A12: ORD000011 | B12: PROD00019 | C12: 2 | D12: =_xlfn.XLOOKUP(order_items!B12,products_2026!A:A,products_2026!C:C,,0,) -> Beauty | E12: =_xlfn.XLOOKUP(B12,products_2026!A:A,products_2026!D:D,,0,) -> 10.94 | F12: =C12*E12 -> 21.88 | G12: =_xlfn.XLOOKUP(B12,products_2026!A:A,products_2026!B:B,,0,) -> Hydrating Face Mist | H12: =_xlfn.XLOOKUP(B12,products_2026!A:A,products_2026!E:E,,0,) -> SELL0017 | I12: =IFERROR(_xlfn.XLOOKUP(H12,sellers_2026!A:A,sellers_2026!G:G,,0,), "unknown/inactive") -> QLD | J12: =_xlfn.XLOOKUP(H12,sellers_2026!A:A,sellers_2026!B:B,,0,) -> 7e16xoz37j | L12: Clothes | M12: 3487.24
A13: ORD000011 | B13: PROD00240 | C13: 1 | D13: =_xlfn.XLOOKUP(order_items!B13,products_2026!A:A,products_2026!C:C,,0,) -> Outdoor | E13: =_xlfn.XLOOKUP(B13,products_2026!A:A,products_2026!D:D,,0,) -> 51.74 | F13: =C13*E13 -> 51.74 | G13: =_xlfn.XLOOKUP(B13,products_2026!A:A,products_2026!B:B,,0,) -> Garden Ornament Frog | H13: =_xlfn.XLOOKUP(B13,products_2026!A:A,products_2026!E:E,,0,) -> SELL0077 | I13: =IFERROR(_xlfn.XLOOKUP(H13,sellers_2026!A:A,sellers_2026!G:G,,0,), "unknown/inactive") -> ACT | J13: =_xlfn.XLOOKUP(H13,sellers_2026!A:A,sellers_2026!B:B,,0,) -> doorsyout | L13: Health | M13: 2178.86
A14: ORD000011 | B14: PROD00409 | C14: 1 | D14: =_xlfn.XLOOKUP(order_items!B14,products_2026!A:A,products_2026!C:C,,0,) -> Clothes | E14: =_xlfn.XLOOKUP(B14,products_2026!A:A,products_2026!D:D,,0,) -> 64.84 | F14: =C14*E14 -> 64.84 | G14: =_xlfn.XLOOKUP(B14,products_2026!A:A,products_2026!B:B,,0,) -> Portable Camping Chair (Blue) | H14: =_xlfn.XLOOKUP(B14,products_2026!A:A,products_2026!E:E,,0,) -> SELL0092 | I14: =IFERROR(_xlfn.XLOOKUP(H14,sellers_2026!A:A,sellers_2026!G:G,,0,), "unknown/inactive") -> VIC | J14: =_xlfn.XLOOKUP(H14,sellers_2026!A:A,sellers_2026!B:B,,0,) -> dress4beauty | L14: Jewellery | M14: 1829.68
A15: ORD000012 | B15: PROD00059 | C15: 1 | D15: =_xlfn.XLOOKUP(order_items!B15,products_2026!A:A,products_2026!C:C,,0,) -> Beauty | E15: =_xlfn.XLOOKUP(B15,products_2026!A:A,products_2026!D:D,,0,) -> 15.04 | F15: =C15*E15 -> 15.04 | G15: =_xlfn.XLOOKUP(B15,products_2026!A:A,products_2026!B:B,,0,) -> Blending Sponge | H15: =_xlfn.XLOOKUP(B15,products_2026!A:A,products_2026!E:E,,0,) -> SELL0032 | I15: =IFERROR(_xlfn.XLOOKUP(H15,sellers_2026!A:A,sellers_2026!G:G,,0,), "unknown/inactive") -> VIC | J15: =_xlfn.XLOOKUP(H15,sellers_2026!A:A,sellers_2026!B:B,,0,) -> buydongxi25 | L15: Gift_Sets | M15: 1807.1
A16: ORD000012 | B16: PROD00324 | C16: 1 | D16: =_xlfn.XLOOKUP(order_items!B16,products_2026!A:A,products_2026!C:C,,0,) -> Gift_Sets | E16: =_xlfn.XLOOKUP(B16,products_2026!A:A,products_2026!D:D,,0,) -> 33.89 | F16: =C16*E16 -> 33.89 | G16: =_xlfn.XLOOKUP(B16,products_2026!A:A,products_2026!B:B,,0,) -> Mini Plant Starter Kit (Diasy) | H16: =_xlfn.XLOOKUP(B16,products_2026!A:A,products_2026!E:E,,0,) -> SELL0088 | I16: =IFERROR(_xlfn.XLOOKUP(H16,sellers_2026!A:A,sellers_2026!G:G,,0,), "unknown/inactive") -> TAS | J16: =_xlfn.XLOOKUP(H16,sellers_2026!A:A,sellers_2026!B:B,,0,) -> 7ti9lfa6h5 | L16: Toys | M16: 1434.61
A17: ORD000013 | B17: PROD00007 | C17: 1 | D17: =_xlfn.XLOOKUP(order_items!B17,products_2026!A:A,products_2026!C:C,,0,) -> Toys | E17: =_xlfn.XLOOKUP(B17,products_2026!A:A,products_2026!D:D,,0,) -> 38.25 | F17: =C17*E17 -> 38.25 | G17: =_xlfn.XLOOKUP(B17,products_2026!A:A,products_2026!B:B,,0,) -> Slime Lab Blue 8pc | H17: =_xlfn.XLOOKUP(B17,products_2026!A:A,products_2026!E:E,,0,) -> SELL0006 | I17: =IFERROR(_xlfn.XLOOKUP(H17,sellers_2026!A:A,sellers_2026!G:G,,0,), "unknown/inactive") -> VIC | J17: =_xlfn.XLOOKUP(H17,sellers_2026!A:A,sellers_2026!B:B,,0,) -> toysyay | L17: Beauty | M17: 1239.08
A18: ORD000014 | B18: PROD00108 | C18: 2 | D18: =_xlfn.XLOOKUP(order_items!B18,products_2026!A:A,products_2026!C:C,,0,) -> Home | E18: =_xlfn.XLOOKUP(B18,products_2026!A:A,products_2026!D:D,,0,) -> 91.41 | F18: =C18*E18 -> 182.82 | G18: =_xlfn.XLOOKUP(B18,products_2026!A:A,products_2026!B:B,,0,) -> Premium Soy Candle Orange Blossom | H18: =_xlfn.XLOOKUP(B18,products_2026!A:A,products_2026!E:E,,0,) -> SELL0042 | I18: =IFERROR(_xlfn.XLOOKUP(H18,sellers_2026!A:A,sellers_2026!G:G,,0,), "unknown/inactive") -> WA | J18: =_xlfn.XLOOKUP(H18,sellers_2026!A:A,sellers_2026!B:B,,0,) -> beauty490 | L18: Stationery | M18: 351.23
A19: ORD000014 | B19: PROD00120 | C19: 1 | D19: =_xlfn.XLOOKUP(order_items!B19,products_2026!A:A,products_2026!C:C,,0,) -> Clothes | E19: =_xlfn.XLOOKUP(B19,products_2026!A:A,products_2026!D:D,,0,) -> 25.48 | F19: =C19*E19 -> 25.48 | G19: =_xlfn.XLOOKUP(B19,products_2026!A:A,products_2026!B:B,,0,) -> Rain Jacket Red XXS | H19: =_xlfn.XLOOKUP(B19,products_2026!A:A,products_2026!E:E,,0,) -> SELL0045 | I19: =IFERROR(_xlfn.XLOOKUP(H19,sellers_2026!A:A,sellers_2026!G:G,,0,), "unknown/inactive") -> NT | J19: =_xlfn.XLOOKUP(H19,sellers_2026!A:A,sellers_2026!B:B,,0,) -> s22ods7z5m | L19: (blank)
A20: ORD000014 | B20: PROD00159 | C20: 1 | D20: =_xlfn.XLOOKUP(order_items!B20,products_2026!A:A,products_2026!C:C,,0,) -> Toys | E20: =_xlfn.XLOOKUP(B20,products_2026!A:A,products_2026!D:D,,0,) -> 13.7 | F20: =C20*E20 -> 13.7 | G20: =_xlfn.XLOOKUP(B20,products_2026!A:A,products_2026!B:B,,0,) -> Kids Paint Kit (Blue) | H20: =_xlfn.XLOOKUP(B20,products_2026!A:A,products_2026!E:E,,0,) -> SELL0047 | I20: =IFERROR(_xlfn.XLOOKUP(H20,sellers_2026!A:A,sellers_2026!G:G,,0,), "unknown/inactive") -> NT | J20: =_xlfn.XLOOKUP(H20,sellers_2026!A:A,sellers_2026!B:B,,0,) -> toymajoy | L20: Grand Total | M20: 39697.21
A21: ORD000015 | B21: PROD00200 | C21: 1 | D21: =_xlfn.XLOOKUP(order_items!B21,products_2026!A:A,products_2026!C:C,,0,) -> Outdoor | E21: =_xlfn.XLOOKUP(B21,products_2026!A:A,products_2026!D:D,,0,) -> 30.95 | F21: =C21*E21 -> 30.95 | G21: =_xlfn.XLOOKUP(B21,products_2026!A:A,products_2026!B:B,,0,) -> BBQ Cleaning Brush | H21: =_xlfn.XLOOKUP(B21,products_2026!A:A,products_2026!E:E,,0,) -> SELL0067 | I21: =IFERROR(_xlfn.XLOOKUP(H21,sellers_2026!A:A,sellers_2026!G:G,,0,), "unknown/inactive") -> WA | J21: =_xlfn.XLOOKUP(H21,sellers_2026!A:A,sellers_2026!B:B,,0,) -> w71bv3mee1
A22: ORD000016 | B22: PROD00172 | C22: 1 | D22: =_xlfn.XLOOKUP(order_items!B22,products_2026!A:A,products_2026!C:C,,0,) -> Gift_Sets | E22: =_xlfn.XLOOKUP(B22,products_2026!A:A,products_2026!D:D,,0,) -> 29.98 | F22: =C22*E22 -> 29.98 | G22: =_xlfn.XLOOKUP(B22,products_2026!A:A,products_2026!B:B,,0,) -> Coffee Sampler Pack | H22: =_xlfn.XLOOKUP(B22,products_2026!A:A,products_2026!E:E,,0,) -> SELL0058 | I22: =IFERROR(_xlfn.XLOOKUP(H22,sellers_2026!A:A,sellers_2026!G:G,,0,), "unknown/inactive") -> QLD | J22: =_xlfn.XLOOKUP(H22,sellers_2026!A:A,sellers_2026!B:B,,0,) -> au6ynzdcy5
A23: ORD000016 | B23: PROD00228 | C23: 1 | D23: =_xlfn.XLOOKUP(order_items!B23,products_2026!A:A,products_2026!C:C,,0,) -> Home | E23: =_xlfn.XLOOKUP(B23,products_2026!A:A,products_2026!D:D,,0,) -> 64.55 | F23: =C23*E23 -> 64.55 | G23: =_xlfn.XLOOKUP(B23,products_2026!A:A,products_2026!B:B,,0,) -> Carbon Fiber Mug Set | H23: =_xlfn.XLOOKUP(B23,products_2026!A:A,products_2026!E:E,,0,) -> SELL0074 | I23: =IFERROR(_xlfn.XLOOKUP(H23,sellers_2026!A:A,sellers_2026!G:G,,0,), "unknown/inactive") -> NT | J23: =_xlfn.XLOOKUP(H23,sellers_2026!A:A,sellers_2026!B:B,,0,) -> springlesprungle3
A24: ORD000017 | B24: PROD00422 | C24: 1 | D24: =_xlfn.XLOOKUP(order_items!B24,products_2026!A:A,products_2026!C:C,,0,) -> Outdoor | E24: =_xlfn.XLOOKUP(B24,products_2026!A:A,products_2026!D:D,,0,) -> 50.15 | F24: =C24*E24 -> 50.15 | G24: =_xlfn.XLOOKUP(B24,products_2026!A:A,products_2026!B:B,,0,) -> Beach Umbrella - UV50+ Floral | H24: =_xlfn.XLOOKUP(B24,products_2026!A:A,products_2026!E:E,,0,) -> SELL0092 | I24: =IFERROR(_xlfn.XLOOKUP(H24,sellers_2026!A:A,sellers_2026!G:G,,0,), "unknown/inactive") -> VIC | J24: =_xlfn.XLOOKUP(H24,sellers_2026!A:A,sellers_2026!B:B,,0,) -> dress4beauty
A25: ORD000018 | B25: PROD00360 | C25: 1 | D25: =_xlfn.XLOOKUP(order_items!B25,products_2026!A:A,products_2026!C:C,,0,) -> Home | E25: =_xlfn.XLOOKUP(B25,products_2026!A:A,products_2026!D:D,,0,) -> 20.79 | F25: =C25*E25 -> 20.79 | G25: =_xlfn.XLOOKUP(B25,products_2026!A:A,products_2026!B:B,,0,) -> Silicone Laundry Basket - White | H25: =_xlfn.XLOOKUP(B25,products_2026!A:A,products_2026!E:E,,0,) -> SELL0027 | I25: =IFERROR(_xlfn.XLOOKUP(H25,sellers_2026!A:A,sellers_2026!G:G,,0,), "unknown/inactive") -> QLD | J25: =_xlfn.XLOOKUP(H25,sellers_2026!A:A,sellers_2026!B:B,,0,) -> home458
A26: ORD000019 | B26: PROD00084 | C26: 2 | D26: =_xlfn.XLOOKUP(order_items!B26,products_2026!A:A,products_2026!C:C,,0,) -> Home | E26: =_xlfn.XLOOKUP(B26,products_2026!A:A,products_2026!D:D,,0,) -> 46.55 | F26: =C26*E26 -> 93.1 | G26: =_xlfn.XLOOKUP(B26,products_2026!A:A,products_2026!B:B,,0,) -> Stainless Steel Cutting Board | H26: =_xlfn.XLOOKUP(B26,products_2026!A:A,products_2026!E:E,,0,) -> SELL0037 | I26: =IFERROR(_xlfn.XLOOKUP(H26,sellers_2026!A:A,sellers_2026!G:G,,0,), "unknown/inactive") -> VIC | J26: =_xlfn.XLOOKUP(H26,sellers_2026!A:A,sellers_2026!B:B,,0,) -> storeshop | L26: Row Labels | M26: Sum of item_revenue | O26: Row Labels | P26: Sum of product_quantity | R26: Row Labels | S26: Average of product_price | U26: Row Labels | V26: Count of seller_id | X26: Row Labels | Y26: Sum of item_revenue
A27: ORD000020 | B27: PROD00142 | C27: 1 | D27: =_xlfn.XLOOKUP(order_items!B27,products_2026!A:A,products_2026!C:C,,0,) -> Electronics | E27: =_xlfn.XLOOKUP(B27,products_2026!A:A,products_2026!D:D,,0,) -> 62.17 | F27: =C27*E27 -> 62.17 | G27: =_xlfn.XLOOKUP(B27,products_2026!A:A,products_2026!B:B,,0,) -> Bluetooth Speaker - Portable | H27: =_xlfn.XLOOKUP(B27,products_2026!A:A,products_2026!E:E,,0,) -> SELL0051 | I27: =IFERROR(_xlfn.XLOOKUP(H27,sellers_2026!A:A,sellers_2026!G:G,,0,), "unknown/inactive") -> NT | J27: =_xlfn.XLOOKUP(H27,sellers_2026!A:A,sellers_2026!B:B,,0,) -> healthway | L27: Solar Garden Light Set (8 pack) | M27: 923.12 | O27: BBQ Skewers - 12 pack (Bamboo) | P27: 20 | R27: Beauty | S27: 20.6312 | U27: ACT | V27: 43 | X27: ACT | Y27: 2798.11
A28: ORD000021 | B28: PROD00196 | C28: 1 | D28: =_xlfn.XLOOKUP(order_items!B28,products_2026!A:A,products_2026!C:C,,0,) -> Toys | E28: =_xlfn.XLOOKUP(B28,products_2026!A:A,products_2026!D:D,,0,) -> 37.9 | F28: =C28*E28 -> 37.9 | G28: =_xlfn.XLOOKUP(B28,products_2026!A:A,products_2026!B:B,,0,) -> Kite Rainbow | H28: =_xlfn.XLOOKUP(B28,products_2026!A:A,products_2026!E:E,,0,) -> SELL0065 | I28: =IFERROR(_xlfn.XLOOKUP(H28,sellers_2026!A:A,sellers_2026!G:G,,0,), "unknown/inactive") -> ACT | J28: =_xlfn.XLOOKUP(H28,sellers_2026!A:A,sellers_2026!B:B,,0,) -> fq9rb8o3qr | L28: Camping Kettle 5L Navy | M28: 638.9 | O28: Bamboo Picnic Rug Recycled Material | P28: 20 | R28: Clothes | S28: 42.040282 | U28: NSW | V28: 45 | X28: NSW | Y28: 2182.1
A29: ORD000022 | B29: PROD00198 | C29: 1 | D29: =_xlfn.XLOOKUP(order_items!B29,products_2026!A:A,products_2026!C:C,,0,) -> Toys | E29: =_xlfn.XLOOKUP(B29,products_2026!A:A,products_2026!D:D,,0,) -> 24.19 | F29: =C29*E29 -> 24.19 | G29: =_xlfn.XLOOKUP(B29,products_2026!A:A,products_2026!B:B,,0,) -> Light up lawnmower AI powered | H29: =_xlfn.XLOOKUP(B29,products_2026!A:A,products_2026!E:E,,0,) -> SELL0067 | I29: =IFERROR(_xlfn.XLOOKUP(H29,sellers_2026!A:A,sellers_2026!G:G,,0,), "unknown/inactive") -> WA | J29: =_xlfn.XLOOKUP(H29,sellers_2026!A:A,sellers_2026!B:B,,0,) -> w71bv3mee1 | L29: Portable Camping Chair (Yellow) | M29: 601.46 | O29: Snorkel Set - Adult Small | P29: 18 | R29: Electronics | S29: 68.197627 | U29: NT | V29: 135 | X29: NT | Y29: 6315.35
A30: ORD000023 | B30: PROD00362 | C30: 1 | D30: =_xlfn.XLOOKUP(order_items!B30,products_2026!A:A,products_2026!C:C,,0,) -> Home | E30: =_xlfn.XLOOKUP(B30,products_2026!A:A,products_2026!D:D,,0,) -> 115.49 | F30: =C30*E30 -> 115.49 | G30: =_xlfn.XLOOKUP(B30,products_2026!A:A,products_2026!B:B,,0,) -> Memory Foam Pillow Medium Firm | H30: =_xlfn.XLOOKUP(B30,products_2026!A:A,products_2026!E:E,,0,) -> SELL0027 | I30: =IFERROR(_xlfn.XLOOKUP(H30,sellers_2026!A:A,sellers_2026!G:G,,0,), "unknown/inactive") -> QLD | J30: =_xlfn.XLOOKUP(H30,sellers_2026!A:A,sellers_2026!B:B,,0,) -> home458 | L30: Portable Mini Grill | M30: 588.95 | O30: BBQ Cleaning Brush | P30: 15 | R30: Gift_Sets | S30: 29.659423 | U30: QLD | V30: 128 | X30: QLD | Y30: 6542.57
A31: ORD000024 | B31: PROD00197 | C31: 1 | D31: =_xlfn.XLOOKUP(order_items!B31,products_2026!A:A,products_2026!C:C,,0,) -> Health | E31: =_xlfn.XLOOKUP(B31,products_2026!A:A,products_2026!D:D,,0,) -> 40.75 | F31: =C31*E31 -> 40.75 | G31: =_xlfn.XLOOKUP(B31,products_2026!A:A,products_2026!B:B,,0,) -> Blood Pressure Monitor Digital | H31: =_xlfn.XLOOKUP(B31,products_2026!A:A,products_2026!E:E,,0,) -> SELL0066 | I31: =IFERROR(_xlfn.XLOOKUP(H31,sellers_2026!A:A,sellers_2026!G:G,,0,), "unknown/inactive") -> VIC | J31: =_xlfn.XLOOKUP(H31,sellers_2026!A:A,sellers_2026!B:B,,0,) -> healthcarehelp | L31: Snorkel Set - Adult Small | M31: 588.06 | O31: Waterproof Picnic Mat 100x100 | P31: 12 | R31: Health | S31: 47.101707 | U31: SA | V31: 12 | X31: SA | Y31: 680.99
A32: ORD000025 | B32: PROD00211 | C32: 1 | D32: =_xlfn.XLOOKUP(order_items!B32,products_2026!A:A,products_2026!C:C,,0,) -> Home | E32: =_xlfn.XLOOKUP(B32,products_2026!A:A,products_2026!D:D,,0,) -> 14.98 | F32: =C32*E32 -> 14.98 | G32: =_xlfn.XLOOKUP(B32,products_2026!A:A,products_2026!B:B,,0,) -> Essential Oil Diffuser Mains Powered | H32: =_xlfn.XLOOKUP(B32,products_2026!A:A,products_2026!E:E,,0,) -> SELL0070 | I32: =IFERROR(_xlfn.XLOOKUP(H32,sellers_2026!A:A,sellers_2026!G:G,,0,), "unknown/inactive") -> QLD | J32: =_xlfn.XLOOKUP(H32,sellers_2026!A:A,sellers_2026!B:B,,0,) -> homeandaways | L32: BBQ Apron - Blue | M32: 560.49 | O32: Fairy Lights Outdoor Garden String 100 | P32: 12 | R32: Home | S32: 59.057079 | U32: TAS | V32: 158 | X32: TAS | Y32: 8013.18
A33: ORD000025 | B33: PROD00315 | C33: 2 | D33: =_xlfn.XLOOKUP(order_items!B33,products_2026!A:A,products_2026!C:C,,0,) -> Electronics | E33: =_xlfn.XLOOKUP(B33,products_2026!A:A,products_2026!D:D,,0,) -> 36.57 | F33: =C33*E33 -> 73.14 | G33: =_xlfn.XLOOKUP(B33,products_2026!A:A,products_2026!B:B,,0,) -> Portable Power Bank 10,000mAh (Navy) | H33: =_xlfn.XLOOKUP(B33,products_2026!A:A,products_2026!E:E,,0,) -> SELL0088 | I33: =IFERROR(_xlfn.XLOOKUP(H33,sellers_2026!A:A,sellers_2026!G:G,,0,), "unknown/inactive") -> TAS | J33: =_xlfn.XLOOKUP(H33,sellers_2026!A:A,sellers_2026!B:B,,0,) -> 7ti9lfa6h5 | L33: Waterproof Picnic Mat 100x100 | M33: 519.42 | O33: Stainless Steel BBQ Tools Set (Navy) | P33: 10 | R33: Jewellery | S33: 35.403617 | U33: VIC | V33: 186 | X33: VIC | Y33: 9289.27
A34: ORD000025 | B34: PROD00404 | C34: 1 | D34: =_xlfn.XLOOKUP(order_items!B34,products_2026!A:A,products_2026!C:C,,0,) -> Outdoor | E34: =_xlfn.XLOOKUP(B34,products_2026!A:A,products_2026!D:D,,0,) -> 81.02 | F34: =C34*E34 -> 81.02 | G34: =_xlfn.XLOOKUP(B34,products_2026!A:A,products_2026!B:B,,0,) -> BBQ Meat Thermometer Bluetooth | H34: =_xlfn.XLOOKUP(B34,products_2026!A:A,products_2026!E:E,,0,) -> SELL0092 | I34: =IFERROR(_xlfn.XLOOKUP(H34,sellers_2026!A:A,sellers_2026!G:G,,0,), "unknown/inactive") -> VIC | J34: =_xlfn.XLOOKUP(H34,sellers_2026!A:A,sellers_2026!B:B,,0,) -> dress4beauty | L34: Garden Ornament Frog | M34: 517.4 | O34: Vitamin C Serum 50ml | P34: 10 | R34: Outdoor | S34: 47.986186 | U34: WA | V34: 88 | X34: WA | Y34: 3875.64
A35: ORD000026 | B35: PROD00087 | C35: 2 | D35: =_xlfn.XLOOKUP(order_items!B35,products_2026!A:A,products_2026!C:C,,0,) -> Home | E35: =_xlfn.XLOOKUP(B35,products_2026!A:A,products_2026!D:D,,0,) -> 82.88 | F35: =C35*E35 -> 165.76 | G35: =_xlfn.XLOOKUP(B35,products_2026!A:A,products_2026!B:B,,0,) -> Floor Lamp Standing Tall LED | H35: =_xlfn.XLOOKUP(B35,products_2026!A:A,products_2026!E:E,,0,) -> SELL0038 | I35: =IFERROR(_xlfn.XLOOKUP(H35,sellers_2026!A:A,sellers_2026!G:G,,0,), "unknown/inactive") -> SA | J35: =_xlfn.XLOOKUP(H35,sellers_2026!A:A,sellers_2026!B:B,,0,) -> compradadonut | L35: Smart LED Light Bulb | M35: 509.41 | O35: Camping Kettle 5L Navy | P35: 10 | R35: Stationery | S35: 7.5887179 | U35: (blank) | X35: (blank)
A36: ORD000027 | B36: PROD00215 | C36: 2 | D36: =_xlfn.XLOOKUP(order_items!B36,products_2026!A:A,products_2026!C:C,,0,) -> Home | E36: =_xlfn.XLOOKUP(B36,products_2026!A:A,products_2026!D:D,,0,) -> 19.99 | F36: =C36*E36 -> 39.98 | G36: =_xlfn.XLOOKUP(B36,products_2026!A:A,products_2026!B:B,,0,) -> Drawer Organiser 5 sections | H36: =_xlfn.XLOOKUP(B36,products_2026!A:A,products_2026!E:E,,0,) -> SELL0070 | I36: =IFERROR(_xlfn.XLOOKUP(H36,sellers_2026!A:A,sellers_2026!G:G,,0,), "unknown/inactive") -> QLD | J36: =_xlfn.XLOOKUP(H36,sellers_2026!A:A,sellers_2026!B:B,,0,) -> homeandaways | L36: BBQ Meat Thermometer Bluetooth | M36: 486.12 | O36: Garden Ornament Frog | P36: 10 | R36: Toys | S36: 23.85625 | U36: Grand Total | V36: 795 | X36: Grand Total | Y36: 39697.21
A37: ORD000028 | B37: PROD00276 | C37: 1 | D37: =_xlfn.XLOOKUP(order_items!B37,products_2026!A:A,products_2026!C:C,,0,) -> Clothes | E37: =_xlfn.XLOOKUP(B37,products_2026!A:A,products_2026!D:D,,0,) -> 44.13 | F37: =C37*E37 -> 44.13 | G37: =_xlfn.XLOOKUP(B37,products_2026!A:A,products_2026!B:B,,0,) -> Men’s Chino Shorts XL | H37: =_xlfn.XLOOKUP(B37,products_2026!A:A,products_2026!E:E,,0,) -> SELL0086 | I37: =IFERROR(_xlfn.XLOOKUP(H37,sellers_2026!A:A,sellers_2026!G:G,,0,), "unknown/inactive") -> VIC | J37: =_xlfn.XLOOKUP(H37,sellers_2026!A:A,sellers_2026!B:B,,0,) -> clothesforlife | L37: Memory Foam Pillow Medium Firm x 2 | M37: 477.2 | O37: Garden Light Sun Powered No Recharge | P37: 9 | R37: (blank)
A38: ORD000029 | B38: PROD00234 | C38: 1 | D38: =_xlfn.XLOOKUP(order_items!B38,products_2026!A:A,products_2026!C:C,,0,) -> Clothes | E38: =_xlfn.XLOOKUP(B38,products_2026!A:A,products_2026!D:D,,0,) -> 20.75 | F38: =C38*E38 -> 20.75 | G38: =_xlfn.XLOOKUP(B38,products_2026!A:A,products_2026!B:B,,0,) -> Wool Beanie - Navy | H38: =_xlfn.XLOOKUP(B38,products_2026!A:A,products_2026!E:E,,0,) -> SELL0039 | I38: =IFERROR(_xlfn.XLOOKUP(H38,sellers_2026!A:A,sellers_2026!G:G,,0,), "unknown/inactive") -> QLD | J38: =_xlfn.XLOOKUP(H38,sellers_2026!A:A,sellers_2026!B:B,,0,) -> zmkizlf6t6 | L38: BBQ Cleaning Brush | M38: 464.25 | O38: Stainless Steel Grill Basket | P38: 9 | R38: Grand Total | S38: 42.804377
A39: ORD000029 | B39: PROD00425 | C39: 1 | D39: =_xlfn.XLOOKUP(order_items!B39,products_2026!A:A,products_2026!C:C,,0,) -> Outdoor | E39: =_xlfn.XLOOKUP(B39,products_2026!A:A,products_2026!D:D,,0,) -> 26.98 | F39: =C39*E39 -> 26.98 | G39: =_xlfn.XLOOKUP(B39,products_2026!A:A,products_2026!B:B,,0,) -> Stainless Steel BBQ Tools Set (Grey) | H39: =_xlfn.XLOOKUP(B39,products_2026!A:A,products_2026!E:E,,0,) -> SELL0093 | I39: =IFERROR(_xlfn.XLOOKUP(H39,sellers_2026!A:A,sellers_2026!G:G,,0,), "unknown/inactive") -> NT | J39: =_xlfn.XLOOKUP(H39,sellers_2026!A:A,sellers_2026!B:B,,0,) -> millies-outdoor-shop | L39: Fairy Lights Outdoor Garden String 100 | M39: 460.68 | O39: BBQ Skewers - 12 pack (Stainless Steel) | P39: 9
A40: ORD000030 | B40: PROD00101 | C40: 1 | D40: =_xlfn.XLOOKUP(order_items!B40,products_2026!A:A,products_2026!C:C,,0,) -> Gift_Sets | E40: =_xlfn.XLOOKUP(B40,products_2026!A:A,products_2026!D:D,,0,) -> 32.44 | F40: =C40*E40 -> 32.44 | G40: =_xlfn.XLOOKUP(B40,products_2026!A:A,products_2026!B:B,,0,) -> Dark Chocolate Selection Box | H40: =_xlfn.XLOOKUP(B40,products_2026!A:A,products_2026!E:E,,0,) -> SELL0041 | I40: =IFERROR(_xlfn.XLOOKUP(H40,sellers_2026!A:A,sellers_2026!G:G,,0,), "unknown/inactive") -> NT | J40: =_xlfn.XLOOKUP(H40,sellers_2026!A:A,sellers_2026!B:B,,0,) -> wcs62ctlxh | L40: Compact Hiking Backpack 20L (Blue) | M40: 456.44 | O40: Solar Garden Light Set (8 pack) | P40: 8 | R40: Row Labels | S40: Sum of item_revenue | U40: Row Labels | V40: Sum of product_quantity | X40: Sum of item_revenue | Y40: Column Labels
A41: ORD000031 | B41: PROD00137 | C41: 1 | D41: =_xlfn.XLOOKUP(order_items!B41,products_2026!A:A,products_2026!C:C,,0,) -> Stationery | E41: =_xlfn.XLOOKUP(B41,products_2026!A:A,products_2026!D:D,,0,) -> 7.57 | F41: =C41*E41 -> 7.57 | G41: =_xlfn.XLOOKUP(B41,products_2026!A:A,products_2026!B:B,,0,) -> Whiteoard Markers - 3 pack | H41: =_xlfn.XLOOKUP(B41,products_2026!A:A,products_2026!E:E,,0,) -> SELL0049 | I41: =IFERROR(_xlfn.XLOOKUP(H41,sellers_2026!A:A,sellers_2026!G:G,,0,), "unknown/inactive") -> VIC | J41: =_xlfn.XLOOKUP(H41,sellers_2026!A:A,sellers_2026!B:B,,0,) -> beautifullife472 | L41: Ice bucket outdoor beers garden picnic | M41: 451.44 | O41: Steel Grill Basket | P41: 8 | R41: millies-outdoor-shop | S41: 3154.1 | U41: dress4beauty | V41: 65 | X41: Row Labels | Y41: Beauty | Z41: Clothes | AA41: Electronics | AB41: Gift_Sets | AC41: Health | AD41: Home | AE41: Jewellery | AF41: Outdoor | AG41: Stationery | AH41: Toys | AI41: (blank) | AJ41: Grand Total
A42: ORD000032 | B42: PROD00401 | C42: 1 | D42: =_xlfn.XLOOKUP(order_items!B42,products_2026!A:A,products_2026!C:C,,0,) -> Jewellery | E42: =_xlfn.XLOOKUP(B42,products_2026!A:A,products_2026!D:D,,0,) -> 39.04 | F42: =C42*E42 -> 39.04 | G42: =_xlfn.XLOOKUP(B42,products_2026!A:A,products_2026!B:B,,0,) -> Gold-plated Hoop Earrings 5mm | H42: =_xlfn.XLOOKUP(B42,products_2026!A:A,products_2026!E:E,,0,) -> SELL0092 | I42: =IFERROR(_xlfn.XLOOKUP(H42,sellers_2026!A:A,sellers_2026!G:G,,0,), "unknown/inactive") -> VIC | J42: =_xlfn.XLOOKUP(H42,sellers_2026!A:A,sellers_2026!B:B,,0,) -> dress4beauty | L42: BBQ - Charcoal | M42: 450.6 | O42: BBQ Grill Mat - Non‑stick (Navy) | P42: 7 | R42: dress4beauty | S42: 2733.41 | U42: millies-outdoor-shop | V42: 54 | X42: ACT | Y42: 51.56 | Z42: 84.22 | AB42: 54.47 | AC42: 48.8 | AD42: 11.91 | AE42: 35.02 | AF42: 2436.33 | AH42: 75.8 | AJ42: 2798.11
A43: ORD000032 | B43: PROD00457 | C43: 1 | D43: =_xlfn.XLOOKUP(order_items!B43,products_2026!A:A,products_2026!C:C,,0,) -> Toys | E43: =_xlfn.XLOOKUP(B43,products_2026!A:A,products_2026!D:D,,0,) -> 24.92 | F43: =C43*E43 -> 24.92 | G43: =_xlfn.XLOOKUP(B43,products_2026!A:A,products_2026!B:B,,0,) -> building blocks 800 pc | H43: =_xlfn.XLOOKUP(B43,products_2026!A:A,products_2026!E:E,,0,) -> SELL0095 | I43: =IFERROR(_xlfn.XLOOKUP(H43,sellers_2026!A:A,sellers_2026!G:G,,0,), "unknown/inactive") -> TAS | J43: =_xlfn.XLOOKUP(H43,sellers_2026!A:A,sellers_2026!B:B,,0,) -> toybuy | L43: HD Webcam 1080p USB Desktop | M43: 443.19 | O43: BBQ Apron - Blue | P43: 7 | R43: 7ti9lfa6h5 | S43: 2038.12 | U43: 7ti9lfa6h5 | V43: 49 | X43: NSW | Y43: 467.35 | AA43: 511.84 | AB43: 57.09 | AD43: 211.37 | AE43: 176.8 | AF43: 725.21 | AH43: 32.44 | AJ43: 2182.1
A44: ORD000033 | B44: PROD00050 | C44: 1 | D44: =_xlfn.XLOOKUP(order_items!B44,products_2026!A:A,products_2026!C:C,,0,) -> Home | E44: =_xlfn.XLOOKUP(B44,products_2026!A:A,products_2026!D:D,,0,) -> 29.36 | F44: =C44*E44 -> 29.36 | G44: =_xlfn.XLOOKUP(B44,products_2026!A:A,products_2026!B:B,,0,) -> Essential Oil Diffuser | H44: =_xlfn.XLOOKUP(B44,products_2026!A:A,products_2026!E:E,,0,) -> SELL0028 | I44: =IFERROR(_xlfn.XLOOKUP(H44,sellers_2026!A:A,sellers_2026!G:G,,0,), "unknown/inactive") -> NT | J44: =_xlfn.XLOOKUP(H44,sellers_2026!A:A,sellers_2026!B:B,,0,) -> goodsahoy | L44: Memory Foam Pillow Firm | M44: 440.4 | O44: Outdoor Oven Gloves (Red) | P44: 7 | R44: home458 | S44: 1662.09 | U44: homeandaways | V44: 32 | X44: NT | Y44: 116.19 | Z44: 225.43 | AA44: 62.17 | AB44: 81.82 | AC44: 928.16 | AD44: 504.99 | AE44: 116.9 | AF44: 3810.52 | AG44: 41.27 | AH44: 427.9 | AJ44: 6315.35
A45: ORD000033 | B45: PROD00187 | C45: 1 | D45: =_xlfn.XLOOKUP(order_items!B45,products_2026!A:A,products_2026!C:C,,0,) -> Jewellery | E45: =_xlfn.XLOOKUP(B45,products_2026!A:A,products_2026!D:D,,0,) -> 24.7 | F45: =C45*E45 -> 24.7 | G45: =_xlfn.XLOOKUP(B45,products_2026!A:A,products_2026!B:B,,0,) -> antique bronze necklace owl vintage | H45: =_xlfn.XLOOKUP(B45,products_2026!A:A,products_2026!E:E,,0,) -> SELL0062 | I45: =IFERROR(_xlfn.XLOOKUP(H45,sellers_2026!A:A,sellers_2026!G:G,,0,), "unknown/inactive") -> QLD | J45: =_xlfn.XLOOKUP(H45,sellers_2026!A:A,sellers_2026!B:B,,0,) -> queenslandqweenie | L45: Garden Light Sun Powered No Recharge | M45: 439.29 | O45: Disposible Mini Grill | P45: 7 | R45: beautifullhome | S45: 1634.81 | U45: w71bv3mee1 | V45: 30 | X45: QLD | Y45: 32.82 | Z45: 925.67 | AB45: 117.23 | AC45: 688.47 | AD45: 2036.72 | AE45: 403.73 | AF45: 2098.5 | AG45: 50.67 | AH45: 188.76 | AJ45: 6542.57
A46: ORD000034 | B46: PROD00236 | C46: 1 | D46: =_xlfn.XLOOKUP(order_items!B46,products_2026!A:A,products_2026!C:C,,0,) -> Clothes | E46: =_xlfn.XLOOKUP(B46,products_2026!A:A,products_2026!D:D,,0,) -> 34.22 | F46: =C46*E46 -> 34.22 | G46: =_xlfn.XLOOKUP(B46,products_2026!A:A,products_2026!B:B,,0,) -> Wool Beanie - Black | H46: =_xlfn.XLOOKUP(B46,products_2026!A:A,products_2026!E:E,,0,) -> SELL0039 | I46: =IFERROR(_xlfn.XLOOKUP(H46,sellers_2026!A:A,sellers_2026!G:G,,0,), "unknown/inactive") -> QLD | J46: =_xlfn.XLOOKUP(H46,sellers_2026!A:A,sellers_2026!B:B,,0,) -> zmkizlf6t6 | L46: Turtle Ornament Garden | M46: 399.4 | O46: Kite Glitter | P46: 7 | R46: stuff-on-sale | S46: 1219.76 | U46: clothesforlife | V46: 29 | X46: SA | AA46: 109.36 | AB46: 189.2 | AD46: 248.64 | AE46: 104.7 | AH46: 29.09 | AJ46: 680.99
A47: ORD000035 | B47: PROD00090 | C47: 2 | D47: =_xlfn.XLOOKUP(order_items!B47,products_2026!A:A,products_2026!C:C,,0,) -> Home | E47: =_xlfn.XLOOKUP(B47,products_2026!A:A,products_2026!D:D,,0,) -> 42.24 | F47: =C47*E47 -> 84.48 | G47: =_xlfn.XLOOKUP(B47,products_2026!A:A,products_2026!B:B,,0,) -> Reed Oil Diffuser Pomegranate Bay Leaf | H47: =_xlfn.XLOOKUP(B47,products_2026!A:A,products_2026!E:E,,0,) -> SELL0039 | I47: =IFERROR(_xlfn.XLOOKUP(H47,sellers_2026!A:A,sellers_2026!G:G,,0,), "unknown/inactive") -> QLD | J47: =_xlfn.XLOOKUP(H47,sellers_2026!A:A,sellers_2026!B:B,,0,) -> zmkizlf6t6 | L47: Portable Camping Chair (Blue) | M47: 389.04 | O47: BBQ Meat Thermometer Battery Powered | P47: 7 | R47: w71bv3mee1 | S47: 1125.38 | U47: home458 | V47: 27 | X47: TAS | Y47: 32.3 | Z47: 52.53 | AA47: 2347.57 | AB47: 1102.33 | AC47: 131.78 | AD47: 2939.01 | AE47: 177.49 | AF47: 811.22 | AG47: 160.54 | AH47: 258.41 | AJ47: 8013.18
A48: ORD000035 | B48: PROD00119 | C48: 1 | D48: =_xlfn.XLOOKUP(order_items!B48,products_2026!A:A,products_2026!C:C,,0,) -> Outdoor | E48: =_xlfn.XLOOKUP(B48,products_2026!A:A,products_2026!D:D,,0,) -> 51.49 | F48: =C48*E48 -> 51.49 | G48: =_xlfn.XLOOKUP(B48,products_2026!A:A,products_2026!B:B,,0,) -> Solar Garden Light | H48: =_xlfn.XLOOKUP(B48,products_2026!A:A,products_2026!E:E,,0,) -> SELL0045 | I48: =IFERROR(_xlfn.XLOOKUP(H48,sellers_2026!A:A,sellers_2026!G:G,,0,), "unknown/inactive") -> NT | J48: =_xlfn.XLOOKUP(H48,sellers_2026!A:A,sellers_2026!B:B,,0,) -> s22ods7z5m | L48: Women’s Active Leggings (Yellow) | M48: 381.57 | O48: Women’s Active Leggings (Yellow) | P48: 7 | R48: clothesforlife | S48: 1075.58 | U48: beautifullhome | V48: 27 | X48: VIC | Y48: 327.67 | Z48: 1629.55 | AA48: 1277.17 | AB48: 204.96 | AC48: 354.67 | AD48: 139.65 | AE48: 762.4 | AF48: 4252.59 | AG48: 83.42 | AH48: 257.19 | AJ48: 9289.27
A49: ORD000035 | B49: PROD00240 | C49: 1 | D49: =_xlfn.XLOOKUP(order_items!B49,products_2026!A:A,products_2026!C:C,,0,) -> Outdoor | E49: =_xlfn.XLOOKUP(B49,products_2026!A:A,products_2026!D:D,,0,) -> 51.74 | F49: =C49*E49 -> 51.74 | G49: =_xlfn.XLOOKUP(B49,products_2026!A:A,products_2026!B:B,,0,) -> Garden Ornament Frog | H49: =_xlfn.XLOOKUP(B49,products_2026!A:A,products_2026!E:E,,0,) -> SELL0077 | I49: =IFERROR(_xlfn.XLOOKUP(H49,sellers_2026!A:A,sellers_2026!G:G,,0,), "unknown/inactive") -> ACT | J49: =_xlfn.XLOOKUP(H49,sellers_2026!A:A,sellers_2026!B:B,,0,) -> doorsyout | L49: BBQ Grill Mat - Non‑stick (Navy) | M49: 380.87 | O49: Essential Oil Diffuser | P49: 6 | R49: ELEC25B | S49: 1060.39 | U49: abracadabra_002 | V49: 26 | X49: WA | Y49: 211.19 | Z49: 569.84 | AA49: 77.12 | AC49: 26.98 | AD49: 365.64 | AE49: 52.64 | AF49: 2391.88 | AG49: 15.33 | AH49: 165.02 | AJ49: 3875.64
A50: ORD000035 | B50: PROD00379 | C50: 1 | D50: =_xlfn.XLOOKUP(order_items!B50,products_2026!A:A,products_2026!C:C,,0,) -> Home | E50: =_xlfn.XLOOKUP(B50,products_2026!A:A,products_2026!D:D,,0,) -> 22.63 | F50: =C50*E50 -> 22.63 | G50: =_xlfn.XLOOKUP(B50,products_2026!A:A,products_2026!B:B,,0,) -> Vitamin C Serum 50ml | H50: =_xlfn.XLOOKUP(B50,products_2026!A:A,products_2026!E:E,,0,) -> SELL0091 | I50: =IFERROR(_xlfn.XLOOKUP(H50,sellers_2026!A:A,sellers_2026!G:G,,0,), "unknown/inactive") -> TAS | J50: =_xlfn.XLOOKUP(H50,sellers_2026!A:A,sellers_2026!B:B,,0,) -> beautifullhome | L50: Charcoal Starter Chimney XL | M50: 373.76 | O50: Drawer Organiser 5 sections | P50: 6 | R50: homeandaways | S50: 957.46 | U50: excelinall | V50: 24 | X50: (blank)
A51: ORD000036 | B51: PROD00250 | C51: 1 | D51: =_xlfn.XLOOKUP(order_items!B51,products_2026!A:A,products_2026!C:C,,0,) -> Stationery | E51: =_xlfn.XLOOKUP(B51,products_2026!A:A,products_2026!D:D,,0,) -> 6.18 | F51: =C51*E51 -> 6.18 | G51: =_xlfn.XLOOKUP(B51,products_2026!A:A,products_2026!B:B,,0,) -> Highlighter 4pc Yellow | H51: =_xlfn.XLOOKUP(B51,products_2026!A:A,products_2026!E:E,,0,) -> SELL0080 | I51: =IFERROR(_xlfn.XLOOKUP(H51,sellers_2026!A:A,sellers_2026!G:G,,0,), "unknown/inactive") -> TAS | J51: =_xlfn.XLOOKUP(H51,sellers_2026!A:A,sellers_2026!B:B,,0,) -> cpghfp370y | L51: Premium Soy Candle Orange Blossom | M51: 365.64 | O51: Portable Camping Chair (Blue) | P51: 6 | R51: excelinall | S51: 948.93 | U51: zmkizlf6t6 | V51: 23 | X51: Grand Total | Y51: 1239.08 | Z51: 3487.24 | AA51: 4385.23 | AB51: 1807.1 | AC51: 2178.86 | AD51: 6457.93 | AE51: 1829.68 | AF51: 16526.25 | AG51: 351.23 | AH51: 1434.61 | AJ51: 39697.21
A52: ORD000037 | B52: PROD00115 | C52: 1 | D52: =_xlfn.XLOOKUP(order_items!B52,products_2026!A:A,products_2026!C:C,,0,) -> Electronics | E52: =_xlfn.XLOOKUP(B52,products_2026!A:A,products_2026!D:D,,0,) -> 112.5 | F52: =C52*E52 -> 112.5 | G52: =_xlfn.XLOOKUP(B52,products_2026!A:A,products_2026!B:B,,0,) -> Wireless Bluetooth Earbuds Noise Cancel | H52: =_xlfn.XLOOKUP(B52,products_2026!A:A,products_2026!E:E,,0,) -> SELL0024 | I52: =IFERROR(_xlfn.XLOOKUP(H52,sellers_2026!A:A,sellers_2026!G:G,,0,), "unknown/inactive") -> VIC | J52: =_xlfn.XLOOKUP(H52,sellers_2026!A:A,sellers_2026!B:B,,0,) -> ELEC25B | L52: BBQ Cleaning Brush XXL | M52: 363.95 | O52: Portable Camping Chair (Yellow) | P52: 6 | R52: maddie-sells | S52: 916.89 | U52: healthway | V52: 21
A53: ORD000038 | B53: PROD00323 | C53: 1 | D53: =_xlfn.XLOOKUP(order_items!B53,products_2026!A:A,products_2026!C:C,,0,) -> Gift_Sets | E53: =_xlfn.XLOOKUP(B53,products_2026!A:A,products_2026!D:D,,0,) -> 21.81 | F53: =C53*E53 -> 21.81 | G53: =_xlfn.XLOOKUP(B53,products_2026!A:A,products_2026!B:B,,0,) -> White Chocolate Selection Box | H53: =_xlfn.XLOOKUP(B53,products_2026!A:A,products_2026!E:E,,0,) -> SELL0088 | I53: =IFERROR(_xlfn.XLOOKUP(H53,sellers_2026!A:A,sellers_2026!G:G,,0,), "unknown/inactive") -> TAS | J53: =_xlfn.XLOOKUP(H53,sellers_2026!A:A,sellers_2026!B:B,,0,) -> 7ti9lfa6h5 | L53: LED Light Bulb Reusable | M53: 353.16 | O53: Ice bucket outdoor beers garden picnic | P53: 6 | R53: housenice | S53: 904.08 | U53: toymajoy | V53: 18
A54: ORD000039 | B54: PROD00276 | C54: 1 | D54: =_xlfn.XLOOKUP(order_items!B54,products_2026!A:A,products_2026!C:C,,0,) -> Clothes | E54: =_xlfn.XLOOKUP(B54,products_2026!A:A,products_2026!D:D,,0,) -> 44.13 | F54: =C54*E54 -> 44.13 | G54: =_xlfn.XLOOKUP(B54,products_2026!A:A,products_2026!B:B,,0,) -> Men’s Chino Shorts XL | H54: =_xlfn.XLOOKUP(B54,products_2026!A:A,products_2026!E:E,,0,) -> SELL0086 | I54: =IFERROR(_xlfn.XLOOKUP(H54,sellers_2026!A:A,sellers_2026!G:G,,0,), "unknown/inactive") -> VIC | J54: =_xlfn.XLOOKUP(H54,sellers_2026!A:A,sellers_2026!B:B,,0,) -> clothesforlife | L54: Disposible Mini Grill | M54: 336.98 | O54: Portable Power Bank 10,000mAh (Navy) | P54: 6 | R54: healthway | S54: 824.28 | U54: cleaning_out_my_shed | V54: 18
A55: ORD000039 | B55: PROD00290 | C55: 2 | D55: =_xlfn.XLOOKUP(order_items!B55,products_2026!A:A,products_2026!C:C,,0,) -> Clothes | E55: =_xlfn.XLOOKUP(B55,products_2026!A:A,products_2026!D:D,,0,) -> 53.17 | F55: =C55*E55 -> 106.34 | G55: =_xlfn.XLOOKUP(B55,products_2026!A:A,products_2026!B:B,,0,) -> Unisex Hoodie - Yellow L | H55: =_xlfn.XLOOKUP(B55,products_2026!A:A,products_2026!E:E,,0,) -> SELL0039 | I55: =IFERROR(_xlfn.XLOOKUP(H55,sellers_2026!A:A,sellers_2026!G:G,,0,), "unknown/inactive") -> QLD | J55: =_xlfn.XLOOKUP(H55,sellers_2026!A:A,sellers_2026!B:B,,0,) -> zmkizlf6t6 | L55: Noise Cancelling Headphones (Black) | M55: 319.2 | O55: BBQ - Charcoal | P55: 6 | R55: zmkizlf6t6 | S55: 808.1 | U55: ELEC25B | V55: 16
A56: ORD000039 | B56: PROD00428 | C56: 1 | D56: =_xlfn.XLOOKUP(order_items!B56,products_2026!A:A,products_2026!C:C,,0,) -> Outdoor | E56: =_xlfn.XLOOKUP(B56,products_2026!A:A,products_2026!D:D,,0,) -> 114.11 | F56: =C56*E56 -> 114.11 | G56: =_xlfn.XLOOKUP(B56,products_2026!A:A,products_2026!B:B,,0,) -> Compact Hiking Backpack 20L (Blue) | H56: =_xlfn.XLOOKUP(B56,products_2026!A:A,products_2026!E:E,,0,) -> SELL0093 | I56: =IFERROR(_xlfn.XLOOKUP(H56,sellers_2026!A:A,sellers_2026!G:G,,0,), "unknown/inactive") -> NT | J56: =_xlfn.XLOOKUP(H56,sellers_2026!A:A,sellers_2026!B:B,,0,) -> millies-outdoor-shop | L56: Ceramic Vase Grey Sand | M56: 304.65 | O56: BBQ Meat Thermometer Bluetooth | P56: 6 | R56: electrowave | S56: 731.21 | U56: housenice | V56: 16
A57: ORD000040 | B57: PROD00315 | C57: 1 | D57: =_xlfn.XLOOKUP(order_items!B57,products_2026!A:A,products_2026!C:C,,0,) -> Electronics | E57: =_xlfn.XLOOKUP(B57,products_2026!A:A,products_2026!D:D,,0,) -> 36.57 | F57: =C57*E57 -> 36.57 | G57: =_xlfn.XLOOKUP(B57,products_2026!A:A,products_2026!B:B,,0,) -> Portable Power Bank 10,000mAh (Navy) | H57: =_xlfn.XLOOKUP(B57,products_2026!A:A,products_2026!E:E,,0,) -> SELL0088 | I57: =IFERROR(_xlfn.XLOOKUP(H57,sellers_2026!A:A,sellers_2026!G:G,,0,), "unknown/inactive") -> TAS | J57: =_xlfn.XLOOKUP(H57,sellers_2026!A:A,sellers_2026!B:B,,0,) -> 7ti9lfa6h5 | L57: BBQ Apron - Red | M57: 291.51 | O57: Beeswax Candle - Mint Rosemary | P57: 6 | R57: cleaning_out_my_shed | S57: 720.73 | U57: stuff-on-sale | V57: 15
A58: ORD000041 | B58: PROD00056 | C58: 1 | D58: =_xlfn.XLOOKUP(order_items!B58,products_2026!A:A,products_2026!C:C,,0,) -> Health | E58: =_xlfn.XLOOKUP(B58,products_2026!A:A,products_2026!D:D,,0,) -> 58.23 | F58: =C58*E58 -> 58.23 | G58: =_xlfn.XLOOKUP(B58,products_2026!A:A,products_2026!B:B,,0,) -> Yoga Mat 10mm | H58: =_xlfn.XLOOKUP(B58,products_2026!A:A,products_2026!E:E,,0,) -> SELL0031 | I58: =IFERROR(_xlfn.XLOOKUP(H58,sellers_2026!A:A,sellers_2026!G:G,,0,), "unknown/inactive") -> VIC | J58: =_xlfn.XLOOKUP(H58,sellers_2026!A:A,sellers_2026!B:B,,0,) -> keepwells | L58: Vitamin C Serum 50ml | M58: 285.16 | O58: HD Webcam 1080p USB Desktop | P58: 6 | R58: au6ynzdcy5 | S58: 713.98 | U58: storeshop | V58: 15
A59: ORD000041 | B59: PROD00093 | C59: 1 | D59: =_xlfn.XLOOKUP(order_items!B59,products_2026!A:A,products_2026!C:C,,0,) -> Stationery | E59: =_xlfn.XLOOKUP(B59,products_2026!A:A,products_2026!D:D,,0,) -> 12.88 | F59: =C59*E59 -> 12.88 | G59: =_xlfn.XLOOKUP(B59,products_2026!A:A,products_2026!B:B,,0,) -> Highlighter Set Pens Yellow | H59: =_xlfn.XLOOKUP(B59,products_2026!A:A,products_2026!E:E,,0,) -> SELL0040 | I59: =IFERROR(_xlfn.XLOOKUP(H59,sellers_2026!A:A,sellers_2026!G:G,,0,), "unknown/inactive") -> TAS | J59: =_xlfn.XLOOKUP(H59,sellers_2026!A:A,sellers_2026!B:B,,0,) -> cheapandgood27 | L59: Steel Grill Basket | M59: 278.88 | O59: Cotton T‑Shirt Green XL | P59: 5 | R59: beauty490 | S59: 653.91 | U59: maddie-sells | V59: 15
A60: ORD000042 | B60: PROD00363 | C60: 2 | D60: =_xlfn.XLOOKUP(order_items!B60,products_2026!A:A,products_2026!C:C,,0,) -> Home | E60: =_xlfn.XLOOKUP(B60,products_2026!A:A,products_2026!D:D,,0,) -> 46.25 | F60: =C60*E60 -> 92.5 | G60: =_xlfn.XLOOKUP(B60,products_2026!A:A,products_2026!B:B,,0,) -> Memory Foam Pillow Firm x 2 | H60: =_xlfn.XLOOKUP(B60,products_2026!A:A,products_2026!E:E,,0,) -> SELL0027 | I60: =IFERROR(_xlfn.XLOOKUP(H60,sellers_2026!A:A,sellers_2026!G:G,,0,), "unknown/inactive") -> QLD | J60: =_xlfn.XLOOKUP(H60,sellers_2026!A:A,sellers_2026!B:B,,0,) -> home458 | L60: BBQ Skewers - 12 pack (Bamboo) | M60: 274.2 | O60: Solar Garden Light Set | P60: 5 | R60: nhlay6j49a | S60: 619.4 | U60: g5x9v55sct | V60: 15
A61: ORD000043 | B61: PROD00096 | C61: 1 | D61: =_xlfn.XLOOKUP(order_items!B61,products_2026!A:A,products_2026!C:C,,0,) -> Toys | E61: =_xlfn.XLOOKUP(B61,products_2026!A:A,products_2026!D:D,,0,) -> 7.88 | F61: =C61*E61 -> 7.88 | G61: =_xlfn.XLOOKUP(B61,products_2026!A:A,products_2026!B:B,,0,) -> Car racing track automatic launch | H61: =_xlfn.XLOOKUP(B61,products_2026!A:A,products_2026!E:E,,0,) -> SELL0040 | I61: =IFERROR(_xlfn.XLOOKUP(H61,sellers_2026!A:A,sellers_2026!G:G,,0,), "unknown/inactive") -> TAS | J61: =_xlfn.XLOOKUP(H61,sellers_2026!A:A,sellers_2026!B:B,,0,) -> cheapandgood27 | L61: Wireless Keyboard (Navy) | M61: 269.4 | O61: LED Floor Lamp | P61: 5 | R61: r6vd2aojq8 | S61: 597.18 | U61: beauty490 | V61: 14
A62: ORD000043 | B62: PROD00426 | C62: 1 | D62: =_xlfn.XLOOKUP(order_items!B62,products_2026!A:A,products_2026!C:C,,0,) -> Outdoor | E62: =_xlfn.XLOOKUP(B62,products_2026!A:A,products_2026!D:D,,0,) -> 27.32 | F62: =C62*E62 -> 27.32 | G62: =_xlfn.XLOOKUP(B62,products_2026!A:A,products_2026!B:B,,0,) -> Stainless Steel BBQ Tools Set (Green) | H62: =_xlfn.XLOOKUP(B62,products_2026!A:A,products_2026!E:E,,0,) -> SELL0093 | I62: =IFERROR(_xlfn.XLOOKUP(H62,sellers_2026!A:A,sellers_2026!G:G,,0,), "unknown/inactive") -> NT | J62: =_xlfn.XLOOKUP(H62,sellers_2026!A:A,sellers_2026!B:B,,0,) -> millies-outdoor-shop | L62: paddling pool blue inflatable fishes | M62: 267.76 | O62: Noise Cancelling Headphones (Black) | P62: 5 | R62: swanium | S62: 596.93 | U62: outer40 | V62: 14
A63: ORD000044 | B63: PROD00090 | C63: 1 | D63: =_xlfn.XLOOKUP(order_items!B63,products_2026!A:A,products_2026!C:C,,0,) -> Home | E63: =_xlfn.XLOOKUP(B63,products_2026!A:A,products_2026!D:D,,0,) -> 42.24 | F63: =C63*E63 -> 42.24 | G63: =_xlfn.XLOOKUP(B63,products_2026!A:A,products_2026!B:B,,0,) -> Reed Oil Diffuser Pomegranate Bay Leaf | H63: =_xlfn.XLOOKUP(B63,products_2026!A:A,products_2026!E:E,,0,) -> SELL0039 | I63: =IFERROR(_xlfn.XLOOKUP(H63,sellers_2026!A:A,sellers_2026!G:G,,0,), "unknown/inactive") -> QLD | J63: =_xlfn.XLOOKUP(H63,sellers_2026!A:A,sellers_2026!B:B,,0,) -> zmkizlf6t6 | L63: Portable Mini Grill Gas Fire | M63: 264.63 | O63: Spa Pamper Gift Set For Him | P63: 5 | R63: brizzy_bonanza_48 | S63: 539.25 | U63: au6ynzdcy5 | V63: 14
... A127: ORD000083 | B127: PROD00042 | C127: 2 | D127: =_xlfn.XLOOKUP(order_items!B127,products_2026!A:A,products_2026!C:C,,0,) -> Outdoor | E127: =_xlfn.XLOOKUP(B127,products_2026!A:A,products_2026!D:D,,0,) -> 38.39 | F127: =C127*E127 -> 76.78 | G127: =_xlfn.XLOOKUP(B127,products_2026!A:A,products_2026!B:B,,0,) -> Fairy Lights Outdoor Garden String 100 | H127: =_xlfn.XLOOKUP(B127,products_2026!A:A,products_2026!E:E,,0,) -> SELL0023 | I127: =IFERROR(_xlfn.XLOOKUP(H127,sellers_2026!A:A,sellers_2026!G:G,,0,), "unknown/inactive") -> VIC | J127: =_xlfn.XLOOKUP(H127,sellers_2026!A:A,sellers_2026!B:B,,0,) -> cleaning_out_my_shed | L127: Pearl Stud Earrings Genuine Pearl | M127: 116.9 | O127: Heat Therapy Pad Reusable | P127: 3 | R127: staion-bonanza | S127: 10.39 | U127: 3n2ybcn0e4 | V127: 1
A128: ORD000084 | B128: PROD00024 | C128: 1 | D128: =_xlfn.XLOOKUP(order_items!B128,products_2026!A:A,products_2026!C:C,,0,) -> Outdoor | E128: =_xlfn.XLOOKUP(B128,products_2026!A:A,products_2026!D:D,,0,) -> 23.99 | F128: =C128*E128 -> 23.99 | G128: =_xlfn.XLOOKUP(B128,products_2026!A:A,products_2026!B:B,,0,) -> BBQ Skewers - 24 pack (Bamboo) | H128: =_xlfn.XLOOKUP(B128,products_2026!A:A,products_2026!E:E,,0,) -> SELL0018 | I128: =IFERROR(_xlfn.XLOOKUP(H128,sellers_2026!A:A,sellers_2026!G:G,,0,), "unknown/inactive") -> NT | J128: =_xlfn.XLOOKUP(H128,sellers_2026!A:A,sellers_2026!B:B,,0,) -> darwin_beauty | L128: Adjustable Dumbbell 10kg | M128: 116.75 | O128: Milk Chocolate Selection Box | P128: 3 | R128: (blank) | U128: (blank)
A129: ORD000085 | B129: PROD00374 | C129: 1 | D129: =_xlfn.XLOOKUP(order_items!B129,products_2026!A:A,products_2026!C:C,,0,) -> Home | E129: =_xlfn.XLOOKUP(B129,products_2026!A:A,products_2026!D:D,,0,) -> 100.7 | F129: =C129*E129 -> 100.7 | G129: =_xlfn.XLOOKUP(B129,products_2026!A:A,products_2026!B:B,,0,) -> Portable Camping Chair (Yellow) | H129: =_xlfn.XLOOKUP(B129,products_2026!A:A,products_2026!E:E,,0,) -> SELL0027 | I129: =IFERROR(_xlfn.XLOOKUP(H129,sellers_2026!A:A,sellers_2026!G:G,,0,), "unknown/inactive") -> QLD | J129: =_xlfn.XLOOKUP(H129,sellers_2026!A:A,sellers_2026!B:B,,0,) -> home458 | L129: Solar Garden Light Set | M129: 116.65 | O129: Educational Puzzle - Zoo Animals | P129: 3 | R129: Grand Total | S129: 39697.21 | U129: Grand Total | V129: 940
A130: ORD000085 | B130: PROD00442 | C130: 1 | D130: =_xlfn.XLOOKUP(order_items!B130,products_2026!A:A,products_2026!C:C,,0,) -> Outdoor | E130: =_xlfn.XLOOKUP(B130,products_2026!A:A,products_2026!D:D,,0,) -> 44.92 | F130: =C130*E130 -> 44.92 | G130: =_xlfn.XLOOKUP(B130,products_2026!A:A,products_2026!B:B,,0,) -> Waterproof Picnic Mat | H130: =_xlfn.XLOOKUP(B130,products_2026!A:A,products_2026!E:E,,0,) -> SELL0094 | I130: =IFERROR(_xlfn.XLOOKUP(H130,sellers_2026!A:A,sellers_2026!G:G,,0,), "unknown/inactive") -> WA | J130: =_xlfn.XLOOKUP(H130,sellers_2026!A:A,sellers_2026!B:B,,0,) -> excelinall | L130: Yoga Mat 10mm | M130: 116.46 | O130: Floor Lamp Standing Tall LED | P130: 3
A131: ORD000086 | B131: PROD00332 | C131: 1 | D131: =_xlfn.XLOOKUP(order_items!B131,products_2026!A:A,products_2026!C:C,,0,) -> Gift_Sets | E131: =_xlfn.XLOOKUP(B131,products_2026!A:A,products_2026!D:D,,0,) -> 32.99 | F131: =C131*E131 -> 32.99 | G131: =_xlfn.XLOOKUP(B131,products_2026!A:A,products_2026!B:B,,0,) -> Baby Shower Gift Bundle (Yellow) | H131: =_xlfn.XLOOKUP(B131,products_2026!A:A,products_2026!E:E,,0,) -> SELL0088 | I131: =IFERROR(_xlfn.XLOOKUP(H131,sellers_2026!A:A,sellers_2026!G:G,,0,), "unknown/inactive") -> TAS | J131: =_xlfn.XLOOKUP(H131,sellers_2026!A:A,sellers_2026!B:B,,0,) -> 7ti9lfa6h5 | L131: Rug 100cm x 250cm | M131: 115.35 | O131: Waterproof Picnic Mat Tartan | P131: 3
A132: ORD000087 | B132: PROD00038 | C132: 2 | D132: =_xlfn.XLOOKUP(order_items!B132,products_2026!A:A,products_2026!C:C,,0,) -> Outdoor | E132: =_xlfn.XLOOKUP(B132,products_2026!A:A,products_2026!D:D,,0,) -> 45.46 | F132: =C132*E132 -> 90.92 | G132: =_xlfn.XLOOKUP(B132,products_2026!A:A,products_2026!B:B,,0,) -> Outdoor Oven Gloves (Pink) | H132: =_xlfn.XLOOKUP(B132,products_2026!A:A,products_2026!E:E,,0,) -> SELL0022 | I132: =IFERROR(_xlfn.XLOOKUP(H132,sellers_2026!A:A,sellers_2026!G:G,,0,), "unknown/inactive") -> WA | J132: =_xlfn.XLOOKUP(H132,sellers_2026!A:A,sellers_2026!B:B,,0,) -> g5x9v55sct | L132: Garden Lights 10 pack Solar Power | M132: 113.99 | O132: Mini Plant Starter Kit (Lily) | P132: 3
A133: ORD000088 | B133: PROD00232 | C133: 1 | D133: =_xlfn.XLOOKUP(order_items!B133,products_2026!A:A,products_2026!C:C,,0,) -> Outdoor | E133: =_xlfn.XLOOKUP(B133,products_2026!A:A,products_2026!D:D,,0,) -> 75.1 | F133: =C133*E133 -> 75.1 | G133: =_xlfn.XLOOKUP(B133,products_2026!A:A,products_2026!B:B,,0,) -> BBQ - Charcoal | H133: =_xlfn.XLOOKUP(B133,products_2026!A:A,products_2026!E:E,,0,) -> SELL0075 | I133: =IFERROR(_xlfn.XLOOKUP(H133,sellers_2026!A:A,sellers_2026!G:G,,0,), "unknown/inactive") -> NSW | J133: =_xlfn.XLOOKUP(H133,sellers_2026!A:A,sellers_2026!B:B,,0,) -> nhlay6j49a | L133: Noise Cancelling Headphones (White) | M133: 113.45 | O133: Whiteoard Markers - 3 pack | P133: 3
A134: ORD000088 | B134: PROD00444 | C134: 1 | D134: =_xlfn.XLOOKUP(order_items!B134,products_2026!A:A,products_2026!C:C,,0,) -> Outdoor | E134: =_xlfn.XLOOKUP(B134,products_2026!A:A,products_2026!D:D,,0,) -> 20.55 | F134: =C134*E134 -> 20.55 | G134: =_xlfn.XLOOKUP(B134,products_2026!A:A,products_2026!B:B,,0,) -> Stainless Steel Grill Basket | H134: =_xlfn.XLOOKUP(B134,products_2026!A:A,products_2026!E:E,,0,) -> SELL0094 | I134: =IFERROR(_xlfn.XLOOKUP(H134,sellers_2026!A:A,sellers_2026!G:G,,0,), "unknown/inactive") -> WA | J134: =_xlfn.XLOOKUP(H134,sellers_2026!A:A,sellers_2026!B:B,,0,) -> excelinall | L134: Kids Cotton Pyjamas 18month | M134: 113.37 | O134: Mini Plant Starter Kit (Tulip) | P134: 3
A135: ORD000089 | B135: PROD00444 | C135: 1 | D135: =_xlfn.XLOOKUP(order_items!B135,products_2026!A:A,products_2026!C:C,,0,) -> Outdoor | E135: =_xlfn.XLOOKUP(B135,products_2026!A:A,products_2026!D:D,,0,) -> 20.55 | F135: =C135*E135 -> 20.55 | G135: =_xlfn.XLOOKUP(B135,products_2026!A:A,products_2026!B:B,,0,) -> Stainless Steel Grill Basket | H135: =_xlfn.XLOOKUP(B135,products_2026!A:A,products_2026!E:E,,0,) -> SELL0094 | I135: =IFERROR(_xlfn.XLOOKUP(H135,sellers_2026!A:A,sellers_2026!G:G,,0,), "unknown/inactive") -> WA | J135: =_xlfn.XLOOKUP(H135,sellers_2026!A:A,sellers_2026!B:B,,0,) -> excelinall | L135: Men’s Chino Shorts M | M135: 113.34 | O135: Rug 200cm x 220cm | P135: 3
A136: ORD000090 | B136: PROD00374 | C136: 2 | D136: =_xlfn.XLOOKUP(order_items!B136,products_2026!A:A,products_2026!C:C,,0,) -> Home | E136: =_xlfn.XLOOKUP(B136,products_2026!A:A,products_2026!D:D,,0,) -> 100.7 | F136: =C136*E136 -> 201.4 | G136: =_xlfn.XLOOKUP(B136,products_2026!A:A,products_2026!B:B,,0,) -> Portable Camping Chair (Yellow) | H136: =_xlfn.XLOOKUP(B136,products_2026!A:A,products_2026!E:E,,0,) -> SELL0027 | I136: =IFERROR(_xlfn.XLOOKUP(H136,sellers_2026!A:A,sellers_2026!G:G,,0,), "unknown/inactive") -> QLD | J136: =_xlfn.XLOOKUP(H136,sellers_2026!A:A,sellers_2026!B:B,,0,) -> home458 | L136: Fairy Lights Outdoor Garden String 200 | M136: 111.78 | O136: Noise Cancelling Headphones (Blue) | P136: 3
A137: ORD000090 | B137: PROD00404 | C137: 1 | D137: =_xlfn.XLOOKUP(order_items!B137,products_2026!A:A,products_2026!C:C,,0,) -> Outdoor | E137: =_xlfn.XLOOKUP(B137,products_2026!A:A,products_2026!D:D,,0,) -> 81.02 | F137: =C137*E137 -> 81.02 | G137: =_xlfn.XLOOKUP(B137,products_2026!A:A,products_2026!B:B,,0,) -> BBQ Meat Thermometer Bluetooth | H137: =_xlfn.XLOOKUP(B137,products_2026!A:A,products_2026!E:E,,0,) -> SELL0092 | I137: =IFERROR(_xlfn.XLOOKUP(H137,sellers_2026!A:A,sellers_2026!G:G,,0,), "unknown/inactive") -> VIC | J137: =_xlfn.XLOOKUP(H137,sellers_2026!A:A,sellers_2026!B:B,,0,) -> dress4beauty | L137: Stainless Steel BBQ Tools Set (Green) | M137: 109.28 | O137: Silicone Laundry Basket - White | P137: 3
A138: ORD000091 | B138: PROD00041 | C138: 1 | D138: =_xlfn.XLOOKUP(order_items!B138,products_2026!A:A,products_2026!C:C,,0,) -> Beauty | E138: =_xlfn.XLOOKUP(B138,products_2026!A:A,products_2026!D:D,,0,) -> 14.11 | F138: =C138*E138 -> 14.11 | G138: =_xlfn.XLOOKUP(B138,products_2026!A:A,products_2026!B:B,,0,) -> Body Lotion - Shea Butter 500ml | H138: =_xlfn.XLOOKUP(B138,products_2026!A:A,products_2026!E:E,,0,) -> SELL0023 | I138: =IFERROR(_xlfn.XLOOKUP(H138,sellers_2026!A:A,sellers_2026!G:G,,0,), "unknown/inactive") -> VIC | J138: =_xlfn.XLOOKUP(H138,sellers_2026!A:A,sellers_2026!B:B,,0,) -> cleaning_out_my_shed | L138: White Chocolate Selection Box | M138: 109.05 | O138: Fruity Mango Bath Gel Gift Set | P138: 3
A139: ORD000091 | B139: PROD00426 | C139: 1 | D139: =_xlfn.XLOOKUP(order_items!B139,products_2026!A:A,products_2026!C:C,,0,) -> Outdoor | E139: =_xlfn.XLOOKUP(B139,products_2026!A:A,products_2026!D:D,,0,) -> 27.32 | F139: =C139*E139 -> 27.32 | G139: =_xlfn.XLOOKUP(B139,products_2026!A:A,products_2026!B:B,,0,) -> Stainless Steel BBQ Tools Set (Green) | H139: =_xlfn.XLOOKUP(B139,products_2026!A:A,products_2026!E:E,,0,) -> SELL0093 | I139: =IFERROR(_xlfn.XLOOKUP(H139,sellers_2026!A:A,sellers_2026!G:G,,0,), "unknown/inactive") -> NT | J139: =_xlfn.XLOOKUP(H139,sellers_2026!A:A,sellers_2026!B:B,,0,) -> millies-outdoor-shop | L139: Unisex Hoodie - Black XXXL | M139: 108.34 | O139: Car Controlled Phone Remote | P139: 3
A140: ORD000092 | B140: PROD00202 | C140: 2 | D140: =_xlfn.XLOOKUP(order_items!B140,products_2026!A:A,products_2026!C:C,,0,) -> Beauty | E140: =_xlfn.XLOOKUP(B140,products_2026!A:A,products_2026!D:D,,0,) -> 27.55 | F140: =C140*E140 -> 55.1 | G140: =_xlfn.XLOOKUP(B140,products_2026!A:A,products_2026!B:B,,0,) -> Body Lotion Shea Butter 1L | H140: =_xlfn.XLOOKUP(B140,products_2026!A:A,products_2026!E:E,,0,) -> SELL0067 | I140: =IFERROR(_xlfn.XLOOKUP(H140,sellers_2026!A:A,sellers_2026!G:G,,0,), "unknown/inactive") -> WA | J140: =_xlfn.XLOOKUP(H140,sellers_2026!A:A,sellers_2026!B:B,,0,) -> w71bv3mee1 | L140: Unisex Hoodie - Blue XXXL | M140: 108.34 | O140: Wood Chips - Oak | P140: 3
A141: ORD000092 | B141: PROD00255 | C141: 1 | D141: =_xlfn.XLOOKUP(order_items!B141,products_2026!A:A,products_2026!C:C,,0,) -> Outdoor | E141: =_xlfn.XLOOKUP(B141,products_2026!A:A,products_2026!D:D,,0,) -> 31.66 | F141: =C141*E141 -> 31.66 | G141: =_xlfn.XLOOKUP(B141,products_2026!A:A,products_2026!B:B,,0,) -> Wood Chips - Hickory | H141: =_xlfn.XLOOKUP(B141,products_2026!A:A,products_2026!E:E,,0,) -> SELL0081 | I141: =IFERROR(_xlfn.XLOOKUP(H141,sellers_2026!A:A,sellers_2026!G:G,,0,), "unknown/inactive") -> QLD | J141: =_xlfn.XLOOKUP(H141,sellers_2026!A:A,sellers_2026!B:B,,0,) -> brizzy_bonanza_48 | L141: Rug 200cm x 180cm | M141: 107.11 | O141: Gold-plated Hoop Earrings Crystal Clip | P141: 3
... A342: ORD000213 | B342: PROD00265 | C342: 1 | D342: =_xlfn.XLOOKUP(order_items!B342,products_2026!A:A,products_2026!C:C,,0,) -> Beauty | E342: =_xlfn.XLOOKUP(B342,products_2026!A:A,products_2026!D:D,,0,) -> 22.24 | F342: =C342*E342 -> 22.24 | G342: =_xlfn.XLOOKUP(B342,products_2026!A:A,products_2026!B:B,,0,) -> Vitamin C Serum 30ml | H342: =_xlfn.XLOOKUP(B342,products_2026!A:A,products_2026!E:E,,0,) -> SELL0084 | I342: =IFERROR(_xlfn.XLOOKUP(H342,sellers_2026!A:A,sellers_2026!G:G,,0,), "unknown/inactive") -> NSW | J342: =_xlfn.XLOOKUP(H342,sellers_2026!A:A,sellers_2026!B:B,,0,) -> lfmk805jw2 | L342: Weekly Planner Pad | M342: 3.23 | O342: Men’s Leather Band Bracelet | P342: 1
A343: ORD000213 | B343: PROD00311 | C343: 1 | D343: =_xlfn.XLOOKUP(order_items!B343,products_2026!A:A,products_2026!C:C,,0,) -> Electronics | E343: =_xlfn.XLOOKUP(B343,products_2026!A:A,products_2026!D:D,,0,) -> 113.45 | F343: =C343*E343 -> 113.45 | G343: =_xlfn.XLOOKUP(B343,products_2026!A:A,products_2026!B:B,,0,) -> Noise Cancelling Headphones (White) | H343: =_xlfn.XLOOKUP(B343,products_2026!A:A,products_2026!E:E,,0,) -> SELL0088 | I343: =IFERROR(_xlfn.XLOOKUP(H343,sellers_2026!A:A,sellers_2026!G:G,,0,), "unknown/inactive") -> TAS | J343: =_xlfn.XLOOKUP(H343,sellers_2026!A:A,sellers_2026!B:B,,0,) -> 7ti9lfa6h5 | L343: (blank) | O343: (blank)
A344: ORD000214 | B344: PROD00052 | C344: 3 | D344: =_xlfn.XLOOKUP(order_items!B344,products_2026!A:A,products_2026!C:C,,0,) -> Stationery | E344: =_xlfn.XLOOKUP(B344,products_2026!A:A,products_2026!D:D,,0,) -> 7.72 | F344: =C344*E344 -> 23.16 | G344: =_xlfn.XLOOKUP(B344,products_2026!A:A,products_2026!B:B,,0,) -> Glitter Gel Pens 4 pack | H344: =_xlfn.XLOOKUP(B344,products_2026!A:A,products_2026!E:E,,0,) -> SELL0028 | I344: =IFERROR(_xlfn.XLOOKUP(H344,sellers_2026!A:A,sellers_2026!G:G,,0,), "unknown/inactive") -> NT | J344: =_xlfn.XLOOKUP(H344,sellers_2026!A:A,sellers_2026!B:B,,0,) -> goodsahoy | L344: Grand Total | M344: 39697.21 | O344: Grand Total | P344: 940
A345: ORD000214 | B345: PROD00390 | C345: 1 | D345: =_xlfn.XLOOKUP(order_items!B345,products_2026!A:A,products_2026!C:C,,0,) -> Home | E345: =_xlfn.XLOOKUP(B345,products_2026!A:A,products_2026!D:D,,0,) -> 66.88 | F345: =C345*E345 -> 66.88 | G345: =_xlfn.XLOOKUP(B345,products_2026!A:A,products_2026!B:B,,0,) -> Wall Clock - Minimalist (Blue) | H345: =_xlfn.XLOOKUP(B345,products_2026!A:A,products_2026!E:E,,0,) -> SELL0091 | I345: =IFERROR(_xlfn.XLOOKUP(H345,sellers_2026!A:A,sellers_2026!G:G,,0,), "unknown/inactive") -> TAS | J345: =_xlfn.XLOOKUP(H345,sellers_2026!A:A,sellers_2026!B:B,,0,) -> beautifullhome
A346: ORD000215 | B346: PROD00194 | C346: 1 | D346: =_xlfn.XLOOKUP(order_items!B346,products_2026!A:A,products_2026!C:C,,0,) -> Toys | E346: =_xlfn.XLOOKUP(B346,products_2026!A:A,products_2026!D:D,,0,) -> 29.09 | F346: =C346*E346 -> 29.09 | G346: =_xlfn.XLOOKUP(B346,products_2026!A:A,products_2026!B:B,,0,) -> Water Gun Set | H346: =_xlfn.XLOOKUP(B346,products_2026!A:A,products_2026!E:E,,0,) -> SELL0064 | I346: =IFERROR(_xlfn.XLOOKUP(H346,sellers_2026!A:A,sellers_2026!G:G,,0,), "unknown/inactive") -> SA | J346: =_xlfn.XLOOKUP(H346,sellers_2026!A:A,sellers_2026!B:B,,0,) -> fungamesandtoys
A347: ORD000215 | B347: PROD00225 | C347: 1 | D347: =_xlfn.XLOOKUP(order_items!B347,products_2026!A:A,products_2026!C:C,,0,) -> Electronics | E347: =_xlfn.XLOOKUP(B347,products_2026!A:A,products_2026!D:D,,0,) -> 23.36 | F347: =C347*E347 -> 23.36 | G347: =_xlfn.XLOOKUP(B347,products_2026!A:A,products_2026!B:B,,0,) -> USB C Fast Charge 30W | H347: =_xlfn.XLOOKUP(B347,products_2026!A:A,products_2026!E:E,,0,) -> SELL0073 | I347: =IFERROR(_xlfn.XLOOKUP(H347,sellers_2026!A:A,sellers_2026!G:G,,0,), "unknown/inactive") -> NSW | J347: =_xlfn.XLOOKUP(H347,sellers_2026!A:A,sellers_2026!B:B,,0,) -> new-south-sales
A348: ORD000216 | B348: PROD00043 | C348: 1 | D348: =_xlfn.XLOOKUP(order_items!B348,products_2026!A:A,products_2026!C:C,,0,) -> Outdoor | E348: =_xlfn.XLOOKUP(B348,products_2026!A:A,products_2026!D:D,,0,) -> 55.89 | F348: =C348*E348 -> 55.89 | G348: =_xlfn.XLOOKUP(B348,products_2026!A:A,products_2026!B:B,,0,) -> Fairy Lights Outdoor Garden String 200 | H348: =_xlfn.XLOOKUP(B348,products_2026!A:A,products_2026!E:E,,0,) -> SELL0023 | I348: =IFERROR(_xlfn.XLOOKUP(H348,sellers_2026!A:A,sellers_2026!G:G,,0,), "unknown/inactive") -> VIC | J348: =_xlfn.XLOOKUP(H348,sellers_2026!A:A,sellers_2026!B:B,,0,) -> cleaning_out_my_shed
A349: ORD000216 | B349: PROD00117 | C349: 1 | D349: =_xlfn.XLOOKUP(order_items!B349,products_2026!A:A,products_2026!C:C,,0,) -> Jewellery | E349: =_xlfn.XLOOKUP(B349,products_2026!A:A,products_2026!D:D,,0,) -> 13.95 | F349: =C349*E349 -> 13.95 | G349: =_xlfn.XLOOKUP(B349,products_2026!A:A,products_2026!B:B,,0,) -> Anklet - Gold | H349: =_xlfn.XLOOKUP(B349,products_2026!A:A,products_2026!E:E,,0,) -> SELL0044 | I349: =IFERROR(_xlfn.XLOOKUP(H349,sellers_2026!A:A,sellers_2026!G:G,,0,), "unknown/inactive") -> QLD | J349: =_xlfn.XLOOKUP(H349,sellers_2026!A:A,sellers_2026!B:B,,0,) -> everything_nmore
A350: ORD000216 | B350: PROD00368 | C350: 1 | D350: =_xlfn.XLOOKUP(order_items!B350,products_2026!A:A,products_2026!C:C,,0,) -> Home | E350: =_xlfn.XLOOKUP(B350,products_2026!A:A,products_2026!D:D,,0,) -> 101.55 | F350: =C350*E350 -> 101.55 | G350: =_xlfn.XLOOKUP(B350,products_2026!A:A,products_2026!B:B,,0,) -> Ceramic Vase Grey Sand | H350: =_xlfn.XLOOKUP(B350,products_2026!A:A,products_2026!E:E,,0,) -> SELL0090 | I350: =IFERROR(_xlfn.XLOOKUP(H350,sellers_2026!A:A,sellers_2026!G:G,,0,), "unknown/inactive") -> TAS | J350: =_xlfn.XLOOKUP(H350,sellers_2026!A:A,sellers_2026!B:B,,0,) -> housenice
A351: ORD000217 | B351: PROD00012 | C351: 2 | D351: =_xlfn.XLOOKUP(order_items!B351,products_2026!A:A,products_2026!C:C,,0,) -> Stationery | E351: =_xlfn.XLOOKUP(B351,products_2026!A:A,products_2026!D:D,,0,) -> 7.06 | F351: =C351*E351 -> 14.12 | G351: =_xlfn.XLOOKUP(B351,products_2026!A:A,products_2026!B:B,,0,) -> Whiteboard Markers - 6 pack | H351: =_xlfn.XLOOKUP(B351,products_2026!A:A,products_2026!E:E,,0,) -> SELL0010 | I351: =IFERROR(_xlfn.XLOOKUP(H351,sellers_2026!A:A,sellers_2026!G:G,,0,), "unknown/inactive") -> VIC | J351: =_xlfn.XLOOKUP(H351,sellers_2026!A:A,sellers_2026!B:B,,0,) -> hobbylobby
A352: ORD000217 | B352: PROD00219 | C352: 1 | D352: =_xlfn.XLOOKUP(order_items!B352,products_2026!A:A,products_2026!C:C,,0,) -> Outdoor | E352: =_xlfn.XLOOKUP(B352,products_2026!A:A,products_2026!D:D,,0,) -> 74.39 | F352: =C352*E352 -> 74.39 | G352: =_xlfn.XLOOKUP(B352,products_2026!A:A,products_2026!B:B,,0,) -> Waterproof Picnic Mat Tartan | H352: =_xlfn.XLOOKUP(B352,products_2026!A:A,products_2026!E:E,,0,) -> SELL0072 | I352: =IFERROR(_xlfn.XLOOKUP(H352,sellers_2026!A:A,sellers_2026!G:G,,0,), "unknown/inactive") -> ACT | J352: =_xlfn.XLOOKUP(H352,sellers_2026!A:A,sellers_2026!B:B,,0,) -> swanium
A353: ORD000217 | B353: PROD00392 | C353: 1 | D353: =_xlfn.XLOOKUP(order_items!B353,products_2026!A:A,products_2026!C:C,,0,) -> Jewellery | E353: =_xlfn.XLOOKUP(B353,products_2026!A:A,products_2026!D:D,,0,) -> 59.61 | F353: =C353*E353 -> 59.61 | G353: =_xlfn.XLOOKUP(B353,products_2026!A:A,products_2026!B:B,,0,) -> Jewellery Box White Oak | H353: =_xlfn.XLOOKUP(B353,products_2026!A:A,products_2026!E:E,,0,) -> SELL0091 | I353: =IFERROR(_xlfn.XLOOKUP(H353,sellers_2026!A:A,sellers_2026!G:G,,0,), "unknown/inactive") -> TAS | J353: =_xlfn.XLOOKUP(H353,sellers_2026!A:A,sellers_2026!B:B,,0,) -> beautifullhome
A354: ORD000217 | B354: PROD00408 | C354: 1 | D354: =_xlfn.XLOOKUP(order_items!B354,products_2026!A:A,products_2026!C:C,,0,) -> Outdoor | E354: =_xlfn.XLOOKUP(B354,products_2026!A:A,products_2026!D:D,,0,) -> 73.4 | F354: =C354*E354 -> 73.4 | G354: =_xlfn.XLOOKUP(B354,products_2026!A:A,products_2026!B:B,,0,) -> BBQ Meat Thermometer WiFi | H354: =_xlfn.XLOOKUP(B354,products_2026!A:A,products_2026!E:E,,0,) -> SELL0092 | I354: =IFERROR(_xlfn.XLOOKUP(H354,sellers_2026!A:A,sellers_2026!G:G,,0,), "unknown/inactive") -> VIC | J354: =_xlfn.XLOOKUP(H354,sellers_2026!A:A,sellers_2026!B:B,,0,) -> dress4beauty
A355: ORD000218 | B355: PROD00202 | C355: 1 | D355: =_xlfn.XLOOKUP(order_items!B355,products_2026!A:A,products_2026!C:C,,0,) -> Beauty | E355: =_xlfn.XLOOKUP(B355,products_2026!A:A,products_2026!D:D,,0,) -> 27.55 | F355: =C355*E355 -> 27.55 | G355: =_xlfn.XLOOKUP(B355,products_2026!A:A,products_2026!B:B,,0,) -> Body Lotion Shea Butter 1L | H355: =_xlfn.XLOOKUP(B355,products_2026!A:A,products_2026!E:E,,0,) -> SELL0067 | I355: =IFERROR(_xlfn.XLOOKUP(H355,sellers_2026!A:A,sellers_2026!G:G,,0,), "unknown/inactive") -> WA | J355: =_xlfn.XLOOKUP(H355,sellers_2026!A:A,sellers_2026!B:B,,0,) -> w71bv3mee1
A356: ORD000218 | B356: PROD00419 | C356: 1 | D356: =_xlfn.XLOOKUP(order_items!B356,products_2026!A:A,products_2026!C:C,,0,) -> Toys | E356: =_xlfn.XLOOKUP(B356,products_2026!A:A,products_2026!D:D,,0,) -> 26.9 | F356: =C356*E356 -> 26.9 | G356: =_xlfn.XLOOKUP(B356,products_2026!A:A,products_2026!B:B,,0,) -> Building Blocks 600 pcs | H356: =_xlfn.XLOOKUP(B356,products_2026!A:A,products_2026!E:E,,0,) -> SELL0047 | I356: =IFERROR(_xlfn.XLOOKUP(H356,sellers_2026!A:A,sellers_2026!G:G,,0,), "unknown/inactive") -> NT | J356: =_xlfn.XLOOKUP(H356,sellers_2026!A:A,sellers_2026!B:B,,0,) -> toymajoy
... A796: ORD000478 | B796: PROD00370 | C796: 2 | D796: =_xlfn.XLOOKUP(order_items!B796,products_2026!A:A,products_2026!C:C,,0,) -> Home | E796: =_xlfn.XLOOKUP(B796,products_2026!A:A,products_2026!D:D,,0,) -> 24.23 | F796: =C796*E796 -> 48.46 | G796: =_xlfn.XLOOKUP(B796,products_2026!A:A,products_2026!B:B,,0,) -> Rug 200cm x 220cm | H796: =_xlfn.XLOOKUP(B796,products_2026!A:A,products_2026!E:E,,0,) -> SELL0027 | I796: =IFERROR(_xlfn.XLOOKUP(H796,sellers_2026!A:A,sellers_2026!G:G,,0,), "unknown/inactive") -> QLD | J796: =_xlfn.XLOOKUP(H796,sellers_2026!A:A,sellers_2026!B:B,,0,) -> home458

Sheet seller_delivery_status
A1: order_id | B1: product_id | C1: Seller_id | D1: Rating | E1: product_quantity | F1: delivery_status | G1: numerical_delivery
A2: ORD000001 | B2: PROD00077 | C2: SELL0036 | D2: 5 | E2: 1 | F2: Delay | G2: -0.67 | J2: average review per seller
A3: ORD000002 | B3: PROD00191 | C3: SELL0062 | D3: 4 | E3: 1 | F3: Delay | G3: -0.7 | J3: total order per seller
A4: ORD000004 | B4: PROD00204 | C4: SELL0067 | D4: 3 | E4: 1 | F4: Delay | G4: -2.4 | J4: % of poor reviews
A5: ORD000005 | B5: PROD00452 | C5: SELL0010 | D5: 4 | E5: 1 | F5: Delay | G5: -0.6 | J5: best/ worst product
A6: ORD000006 | B6: PROD00084 | C6: SELL0037 | D6: 5 | E6: 1 | F6: Delay | G6: -0.66 | J6: best/ worst seller
A7: ORD000008 | B7: PROD00081 | C7: SELL0037 | D7: 4 | E7: 1 | F7: Delay | G7: -1.51 | J7: count of review
A8: ORD000009 | B8: PROD00171 | C8: SELL0058 | D8: 4 | E8: 1 | F8: Delay | G8: -0.64
A9: ORD000012 | B9: PROD00059 | C9: SELL0032 | D9: 4 | E9: 1 | F9: On time | G9: 0.33
A10: ORD000012 | B10: PROD00324 | C10: SELL0088 | D10: 4 | E10: 1 | F10: On time | G10: 0.33
A11: ORD000015 | B11: PROD00200 | C11: SELL0067 | D11: 2 | E11: 1 | F11: Delay | G11: -1.52
A12: ORD000018 | B12: PROD00360 | C12: SELL0027 | D12: 4 | E12: 1 | F12: Delay | G12: -0.5
A13: ORD000019 | B13: PROD00084 | C13: SELL0037 | D13: 3 | E13: 2 | F13: Delay | G13: -0.62
A14: ORD000020 | B14: PROD00142 | C14: SELL0051 | D14: 3 | E14: 1 | F14: On time | G14: 0.36
A15: ORD000021 | B15: PROD00196 | C15: SELL0065 | D15: 2 | E15: 1 | F15: Delay | G15: -1.45
A16: ORD000025 | B16: PROD00211 | C16: SELL0070 | D16: 5 | E16: 1 | F16: On time | G16: 0.29
A17: ORD000025 | B17: PROD00315 | C17: SELL0088 | D17: 5 | E17: 2 | F17: On time | G17: 0.29
A18: ORD000025 | B18: PROD00404 | C18: SELL0092 | D18: 5 | E18: 1 | F18: On time | G18: 0.29
A19: ORD000027 | B19: PROD00215 | C19: SELL0070 | D19: 5 | E19: 2 | F19: Delay | G19: -0.55
... A365: ORD000478 | B365: PROD00370 | C365: SELL0027 | D365: 4 | E365: 2 | F365: Delay | G365: -1.42

Sheet Sheet1
A1: ORD000001 | B1: ORD000001
A2: ORD000002 | B2: ORD000002
A3: ORD000004 | B3: ORD000004
A4: ORD000005 | B4: ORD000005
A5: ORD000006 | B5: ORD000006
A6: ORD000008 | B6: ORD000008
A7: ORD000009 | B7: ORD000009
A8: ORD000012 | B8: ORD000012
A9: ORD000015 | B9: ORD000015
A10: ORD000018 | B10: ORD000018
A11: ORD000019 | B11: ORD000019
A12: ORD000020 | B12: ORD000020
... A215: ORD000478 | B215: ORD000474
B216: ORD000478

Sheet Reviews
A1: order_id | B1: review_rating | C1: reason_review_product | D1: reason_review_delivery | E1: reason_review_price | F1: reason_review_service | G1: rev_order_date | H1: rev_delivery_est | I1: rev_delivery_date | J1: rev_delivery_duration | K1: rev_delay_on_time | L1: Delivery_status
A2: ORD000001 | B2: 5 | C2: FALSE | D2: FALSE | E2: FALSE | F2: FALSE | G2: 45322.508 | H2: 45333 | I2: 45333.673 | J2: 11.17 | K2: -0.67 | L2: Delay
A3: ORD000002 | B3: 4 | C3: TRUE | D3: FALSE | E3: FALSE | F3: FALSE | G3: 45323.16 | H3: 45329 | I3: 45329.696 | J3: 6.54 | K3: -0.7 | L3: Delay
A4: ORD000004 | B4: 3 | C4: FALSE | D4: TRUE | E4: FALSE | F4: FALSE | G4: 45355.067 | H4: 45359 | I4: 45361.396 | J4: 6.33 | K4: -2.4 | L4: Delay
A5: ORD000005 | B5: 4 | C5: FALSE | D5: FALSE | E5: FALSE | F5: FALSE | G5: 45356.483 | H5: 45358 | I5: 45358.605 | J5: 2.12 | K5: -0.6 | L5: Delay
A6: ORD000006 | B6: 5 | C6: FALSE | D6: TRUE | E6: FALSE | F6: FALSE | G6: 45358.174 | H6: 45363 | I6: 45363.656 | J6: 5.48 | K6: -0.66 | L6: Delay
A7: ORD000008 | B7: 4 | C7: TRUE | D7: TRUE | E7: FALSE | F7: FALSE | G7: 45376.197 | H7: 45381 | I7: 45382.512 | J7: 6.32 | K7: -1.51 | L7: Delay
A8: ORD000009 | B8: 4 | C8: FALSE | D8: FALSE | E8: FALSE | F8: FALSE | G8: 45378.181 | H8: 45386 | I8: 45386.642 | J8: 8.46 | K8: -0.64 | L8: Delay
A9: ORD000012 | B9: 4 | C9: FALSE | D9: FALSE | E9: FALSE | F9: FALSE | G9: 45387.401 | H9: 45397 | I9: 45396.668 | J9: 9.27 | K9: 0.33 | L9: On time
A10: ORD000036 | B10: 1 | C10: FALSE | D10: FALSE | E10: FALSE | F10: FALSE | G10: 45434.082 | H10: 45438 | I10: 45439.711 | J10: 5.63 | K10: -1.71 | L10: Delay
A11: ORD000018 | B11: 4 | C11: FALSE | D11: TRUE | E11: FALSE | F11: FALSE | G11: 45397.276 | H11: 45402 | I11: 45402.501 | J11: 5.22 | K11: -0.5 | L11: Delay
A12: ORD000019 | B12: 3 | C12: FALSE | D12: FALSE | E12: FALSE | F12: FALSE | G12: 45401.793 | H12: 45409 | I12: 45409.622 | J12: 7.83 | K12: -0.62 | L12: Delay
A13: ORD000020 | B13: 3 | C13: FALSE | D13: FALSE | E13: FALSE | F13: FALSE | G13: 45405.79 | H13: 45411 | I13: 45410.64 | J13: 4.85 | K13: 0.36 | L13: On time
... A217: ORD000478 | B217: 4 | C217: TRUE | D217: FALSE | E217: FALSE | F217: FALSE | G217: 46112.512 | H217: 46122 | I217: 46123.425 | J217: 10.91 | K217: -1.42 | L217: Delay
J219: =AVERAGE(Reviews[rev_delivery_duration]) -> 7.4831481 | K219: =AVERAGE(Reviews[rev_delay_on_time]) -> -0.82606481
